{
  "username": "aqu_a_qua",
  "followers_count": 3180,
  "recent_posts": [
    {
      "post_id": "DZuJLedTZSH",
      "caption": "🧜‍♀️💤\n\n잠자리에 들어가는 인어를 방해하지 말 것. \n분노의 꽁침을 맞는 수가 있음. \n\n🧜‍♀️ @aqu_a_qua \n📍 @wavepark__ \n📍 @badive_official \n📸 @tom_freedive",
      "media_type": "IMAGE",
      "product": "FEED",
      "permalink": "https://www.instagram.com/p/DZuJLedTZSH/",
      "thumbnail": "https://scontent-atl3-3.cdninstagram.com/v/t51.82787-15/723918070_18140749906553962_5716628398703831130_n.jpg?stp=dst-jpg_e35_tt6&_nc_cat=108&ig_cache_key=MzkyMjExMjY5NjUyMzAwMzAxNQ%3D%3D.3-ccb7-5&ccb=7-5&_nc_sid=58cdad&efg=eyJ2ZW5jb2RlX3RhZyI6IkZFRUQueHBpZHMuMzI3Ny5zZHIucmVndWxhcl9waG90by5DMyJ9&_nc_ohc=eh4INzITPqsQ7kNvwFW_igg&_nc_oc=AdqaYa3QqZFLIXBDhMahgICjY5UF9AANze7lH7q1NS5WA_wDwqo78R_MLYxE9Js-YOw&_nc_zt=23&_nc_ht=scontent-atl3-3.cdninstagram.com&_nc_gid=VhgvQfYbRi4c5bUIzcbyiQ&_nc_ss=72a8c&oh=00_AQDypbHg4Wt_q02y8lt6MkmUu3DnVtXsIzrb_YAPtJbepg&oe=6A66F4F9",
      "posted_at": "2026-06-18T08:53:56.000Z",
      "is_pinned": false,
      "owner_username": "tom_freedive",
      "metrics": {
        "views": null,
        "likes": 138,
        "comments": 2
      }
    },
    {
      "post_id": "DbBFyOGGq2Z",
      "caption": "#협찬 물에 들어가는 날에 입어주면\n더더욱 기분 좋아지는 티에스나인 코하루🍀🖤\n\n작은 네잎클로버나 달콤한 디저트가 아기자기하게 그려진\n수영복과 함께하는 입수하면 소소하게 행복해져요💓\n\n이번에 착용한 티에스나인의 코하루 블랙은\n깔끔한 블랙 컬러에 아기자기한 포인트가 더해져\n심플하지만 밋밋하지 않은 매력이 있는 디자인이에요.\n\n몸을 안정감 있게 잡아주면서도 움직임은 편해서\n아티스틱 스위밍 중에도 부담 없이 입을 수 있었어요!\n특히 가슴선이 안정적이어서 제일 마음에 들었던☺️\n\n🍀착용 제품\n@tornadosports 티에스나인 코하루 블",
      "media_type": "CAROUSEL_ALBUM",
      "product": "FEED",
      "permalink": "https://www.instagram.com/p/DbBFyOGGq2Z/",
      "thumbnail": "https://instagram.fglw1-1.fna.fbcdn.net/v/t51.82787-15/753446804_18010865672930063_5545237502786026047_n.jpg?stp=dst-jpg_e35_tt6&_nc_cat=110&ig_cache_key=Mzk0NTQ1NjU4NjM0MzEwNTA4NQ%3D%3D.3-ccb7-5&ccb=7-5&_nc_sid=58cdad&efg=eyJ2ZW5jb2RlX3RhZyI6IkNBUk9VU0VMX0lURU0ueHBpZHMuMTQ0MC5zZHIucmVndWxhcl9waG90by5DMyJ9&_nc_ohc=_dn7qFSNC4AQ7kNvwEMHkQv&_nc_oc=Adq_LsIZFYw8eOOfdZIgu90s_STBIaEz1rGtjIMdfoKLcCapC_htptLN5D3_Hkl4Pcg&_nc_zt=23&_nc_ht=instagram.fglw1-1.fna&_nc_gid=7GwO4phxYVX64Z0wUChjXg&_nc_ss=7ca8c&oh=00_AQBzdaWdXO-JVpYDg7awQ6ocuo6xg21bwiS7HeFp_Nyt5A&oe=6A670D3E",
      "posted_at": "2026-07-20T13:52:07.000Z",
      "is_pinned": false,
      "owner_username": "aqu_a_qua",
      "metrics": {
        "views": null,
        "likes": 89,
        "comments": 5
      }
    },
    {
      "post_id": "DMFlYb3PsCg",
      "caption": "옛날 옛적 많은 사람들이 풍요를 기원하며 매일 같이 기도를 올렸던 곳\n\n과거의 영광과 함께 수몰되어 더이상 찾는 사람은 없지만\n\n이제는 인어들의 보금자리가 되어 새로운 전설이 조용히 쓰여지고 있다\n\n🐚🫧\n\n중국 푸저우에 있는 야외 풀장으로 다녀왔던 촬영🩶\n빡센 일정에도 든든한 맴버들 덕분에 즐겁게 무사히 다녀왔습니다!\n\n정말 멋진 풀장이니 다이버/인어 분들 한번쯤 방문해보시면 좋을거 같아요☺️\n\n-\n𝗙𝘂𝘇𝗵𝗼𝘂 𝗧𝗼𝘂𝗿 𝘄𝗶𝘁𝗵\n𝗉𝗁𝗈𝗍𝗈 @tom_freedive \n𝖻𝗎𝖽𝖽𝗒 @diver_freena @zieyalish @ra_bb",
      "media_type": "IMAGE",
      "product": "FEED",
      "permalink": "https://www.instagram.com/p/DMFlYb3PsCg/",
      "thumbnail": "https://scontent-ord5-1.cdninstagram.com/v/t51.82787-15/518470541_17966111672930063_7225855619609973088_n.jpg?stp=dst-jpg_e35_p1080x1080_sh2.08_tt6&_nc_ht=scontent-ord5-1.cdninstagram.com&_nc_cat=111&_nc_oc=Q6cZ2gErU8CIs6oAhKkOY-ndl1RPMe9be453jqekO-QvYEx10sTm_F0CxPYQ64w42dCjS9w&_nc_ohc=e_yw2MCwuPQQ7kNvwEA22HA&_nc_gid=ns1J-pDAdVZUt4NmP7xd7w&edm=ADp7STQBAAAA&ccb=7-5&oh=00_AQCr7OoHWxpqijvo0hF2bEEJwzTjuSopFIJ67VfhdzfdXw&oe=6A671841&_nc_sid=c6f216",
      "posted_at": "2025-07-14T11:54:16.000Z",
      "is_pinned": true,
      "owner_username": "aqu_a_qua",
      "metrics": {
        "views": null,
        "likes": 369,
        "comments": 25
      }
    },
    {
      "post_id": "DYzOqnMmn9n",
      "caption": "요즘은 비키니 슈트에 푹 빠져있어요😎\n\n수영복은 산뜻한 매력이 있다면\n비키니 슈트는 좀 포스 있어 보이는게 매력이랄까?,,\n\n다이브앤세일 원숄더 비키니 슈트는\n팔다리가 없어서 활동성은 좋으면서도\n슈트계의 명품 원단인 야마모토 원단을 사용해서 \n보온력도 챙길 수 있음🩶\n\n수영장에서도 잘 입고 있는 슈트인데\n요거 바다 가서 멋지게 입고 싶어요\n\n언제쯤 다시 또 투어 가보나🥹\n\n✔️착용 제품\n다이브앤세일 슬리브리스 원숄더 히든스트랩 비키니\n@divesl_official @ssodda_",
      "media_type": "CAROUSEL_ALBUM",
      "product": "FEED",
      "permalink": "https://www.instagram.com/p/DYzOqnMmn9n/",
      "thumbnail": "https://scontent-atl3-3.cdninstagram.com/v/t51.82787-15/708254996_18002777048930063_8164889580615452774_n.jpg?stp=dst-jpg_e35_tt6&_nc_cat=110&ig_cache_key=MzkwNTUyNDE4NjkyMTQ3MTU1NA%3D%3D.3-ccb7-5&ccb=7-5&_nc_sid=58cdad&efg=eyJ2ZW5jb2RlX3RhZyI6IkNBUk9VU0VMX0lURU0ueHBpZHMuMTQ0MC5zZHIucmVndWxhcl9waG90by5DMyJ9&_nc_ohc=EVqeYFenaNsQ7kNvwFmmxFN&_nc_oc=AdqgaHN0Bx1rq5_WG8TrEaWRznDlev8NbuL6iYQXHk90evb69lnSsZ6BAmorO1Yz-mI&_nc_zt=23&_nc_ht=scontent-atl3-3.cdninstagram.com&_nc_gid=cZgJuU1ZkP7RojZpAXR21w&_nc_ss=72a8c&oh=00_AQDo97oQgVCfhno_1_XVW5xw8USx99tDodHpLmT3CS14SQ&oe=6A66F821",
      "posted_at": "2026-05-26T11:37:34.000Z",
      "is_pinned": false,
      "owner_username": "aqu_a_qua",
      "metrics": {
        "views": null,
        "likes": 179,
        "comments": 11
      }
    },
    {
      "post_id": "DaJ7PSQGvmO",
      "caption": "4년전의 저로서는 너무나 낯선 모습이지만,\n머메이드&수중댄스 강사 트레이너 과정을 수료했습니다🙈\n\n인어들은 원래 우아하고, 수영도 잘할 것 같지만\n머메이드를 처음 시작할 때의 제 모습은 그렇지 않았어요.\n\n몸이 계속 떠올라서 허우적거리고, 숨도 오래 못 참고\n팔과 다리는 뻣뻣하고 삐걱거리고... \n(공감하시는 인어님들 계시죠😂)\n\n그렇지만 내일은 오늘보다 나아질거라는 믿음으로\n대회도 도전해보고, 공연도 해보고\n또 강사가 되어 저와 비슷한 고민을 하던 학생들을 만나고\n그렇게 하다보니 강사님들을 가르칠 수 있는 기회까지 생겼네요...!",
      "media_type": "CAROUSEL_ALBUM",
      "product": "FEED",
      "permalink": "https://www.instagram.com/p/DaJ7PSQGvmO/",
      "thumbnail": "https://scontent-ord5-1.cdninstagram.com/v/t51.82787-15/730506934_18007569467930063_4420305048502056993_n.jpg?stp=dst-jpg_e35_tt6&_nc_cat=111&ig_cache_key=MzkyOTkxMzg0NDE4OTM3MjI1NA%3D%3D.3-ccb7-5&ccb=7-5&_nc_sid=58cdad&efg=eyJ2ZW5jb2RlX3RhZyI6IkNBUk9VU0VMX0lURU0ueHBpZHMuMTQ0MC5zZHIucmVndWxhcl9waG90by5DMyJ9&_nc_ohc=gVSYcMI8IqAQ7kNvwFGlETX&_nc_oc=Adpgf_XKsWDHX6waj6coMFbOPV77ngKEw7oaOEr48hBvSbmNwqcmncQT9RX25SV3hK4&_nc_zt=23&_nc_ht=scontent-ord5-1.cdninstagram.com&_nc_gid=Fctn6nlZucQViXR4BJJkAw&_nc_ss=72689&oh=00_AQCpNq6I-kODKnzHDmMy21hg4FVDQVksKt96JlC29gZ4zw&oe=6A670F57",
      "posted_at": "2026-06-29T03:41:45.000Z",
      "is_pinned": true,
      "owner_username": "aqu_a_qua",
      "metrics": {
        "views": null,
        "likes": 138,
        "comments": 28
      }
    },
    {
      "post_id": "DY6iajsx8vD",
      "caption": "⠀\n🎉2026 IUPC 머메이드 대회 수상을 축하드립니다🎉\n\n머메이드 팀 부문 1등\n@woods_rim \n@aqu_a_qua\n@renapark.kr \n\n#프리다이빙 #머메이드 #mermaid",
      "media_type": "VIDEO",
      "product": "REELS",
      "permalink": "https://www.instagram.com/p/DY6iajsx8vD/",
      "thumbnail": "https://scontent-ord5-2.cdninstagram.com/v/t51.71878-15/708927971_1913165809388006_5258565312696320737_n.jpg?stp=dst-jpg_e15_tt6&_nc_ht=scontent-ord5-2.cdninstagram.com&_nc_cat=102&_nc_oc=Q6cZ2gGtVgeFlG6XGgFa5M2yaooTPUbLVxt0a__AURPiuEHv9yqQr2sMBGD1qz_Nw1q4qIaR6bvflAewn8_LoU_skyb2&_nc_ohc=AeXc9yvO0e0Q7kNvwFeyJgm&_nc_gid=nKRxs2bDxxyJ8AMDdhdxfw&edm=ADp7STQBAAAA&ccb=7-5&oh=00_AQC_1tqBdJS5U9OtbcLwpQb5Y7rND3-neyqeiVj2E_TK0g&oe=6A67265D&_nc_sid=c6f216",
      "posted_at": "2026-05-29T07:47:06.000Z",
      "is_pinned": false,
      "owner_username": "badive_official",
      "metrics": {
        "views": 7095,
        "likes": 172,
        "comments": 9
      }
    },
    {
      "post_id": "Dafox3gGkO8",
      "caption": "#협찬 바다에 빠져버린 버터 한 조각🧈\n\n은은한 색감이 오히려 더 시선을 더 사로잡는\n라세린의 루미나 버터 옐로우 입어봤어요✨\n\n다른 수영복에서 쉽게 보지 못했던 \n크리미한 버터 옐로우 컬러에\n은은하게 반짝이는 원단이 매력적인 디자인이에요!\n\n연한 컬러지만 화이트 안감이 덧대어 있고\n미들컷이라서 비침 걱정❌ 노출 걱정❌\n편하게 착용하고 활동할 수 있어요.\n\n은은하지만 확실한 존재감이 있는 수영복을 원하신다면\n실물은 훨씬 더 예쁜 루미나 버터 옐로우 추천드려요💛\n\n🧈착용 제품\n@laserin_swim 루미나 버터옐로우\n\n🧈착용 사이즈",
      "media_type": "CAROUSEL_ALBUM",
      "product": "FEED",
      "permalink": "https://www.instagram.com/p/Dafox3gGkO8/",
      "thumbnail": "https://scontent-msp1-1.cdninstagram.com/v/t51.82787-15/742154352_18008837057930063_1988274126194868849_n.jpg?stp=dst-jpg_e35_tt6&_nc_cat=103&ig_cache_key=MzkzNTk0NDc1NjY3NjEzNTI3NQ%3D%3D.3-ccb7-5&ccb=7-5&_nc_sid=58cdad&efg=eyJ2ZW5jb2RlX3RhZyI6IkNBUk9VU0VMX0lURU0ueHBpZHMuMTQ0MC5zZHIucmVndWxhcl9waG90by5DMyJ9&_nc_ohc=zfz5p04jdUoQ7kNvwFbywIm&_nc_oc=AdoCHYXjAveVsqqZdFy3myQp3S5r5zQ7g0RP0msd1EtRrr59kkTbfAbA_oSTc6-PHmM&_nc_zt=23&_nc_ht=scontent-msp1-1.cdninstagram.com&_nc_gid=UG1S16fgeGx0-MYwydVF8g&_nc_ss=7ca8c&oh=00_AQAXVBkcRsotxl9MB86YuYpRiNFgM_oHrjYqAS5mvbgG9w&oe=6A671AB5",
      "posted_at": "2026-07-07T14:03:44.000Z",
      "is_pinned": false,
      "owner_username": "aqu_a_qua",
      "metrics": {
        "views": null,
        "likes": 177,
        "comments": 14
      }
    },
    {
      "post_id": "DaIIfwFmkm0",
      "caption": "#제품제공 요즘 콜라보 맛집인 루프루프의 신상\n여름 분위기 물씬 풍기는 베티붑 컬렉션 입어봤어요❣️\n\n요번 베티붑 컬렉션 중에서는 기존에 출시되었던 디자인을 베티붑 버전으로 리뉴얼해서 나온 디자인들이 있는데\n제가 입은 “스트로베리 테이블”도 베티풉 버전으로 리뉴얼해서 나온 버전이에요!\n\n여름 휴가를 떠나는 듯한 베티붑의 얼굴 일러스트에\n기존 스트로베리 테이블보다 살짝 쿨한 색감이 더해져\n입는 순간 상큼 발랄한 매력이 과즙처럼 터지는\n베티붑 버전의 스트로베리 테이블♥️🍓\n\n루프루프 수영복은 루프루프에서 자체제작한 원단으로\n저는 입을 ",
      "media_type": "CAROUSEL_ALBUM",
      "product": "FEED",
      "permalink": "https://www.instagram.com/p/DaIIfwFmkm0/",
      "thumbnail": "https://scontent-dfw5-2.cdninstagram.com/v/t51.82787-15/731221806_18007453631930063_8097228771570598819_n.jpg?stp=dst-jpg_e35_tt6&_nc_cat=107&ig_cache_key=MzkyOTM5NzIwNTQyMDg2MDQ2Ng%3D%3D.3-ccb7-5&ccb=7-5&_nc_sid=58cdad&efg=eyJ2ZW5jb2RlX3RhZyI6IkNBUk9VU0VMX0lURU0ueHBpZHMuMTQ0MC5zZHIucmVndWxhcl9waG90by5DMyJ9&_nc_ohc=ygE2p_o7-c8Q7kNvwETuDDO&_nc_oc=AdqIfPnsYGk59V8yPUN_Z4Q57GqSlFnNtMbBNHyp4spuOkUBDeDo49OoV6oIzU007Vc&_nc_zt=23&_nc_ht=scontent-dfw5-2.cdninstagram.com&_nc_gid=Tl3saJh-Sq_7ViQFbarVOg&_nc_ss=72a8c&oh=00_AQDltaYIZiBktLeimrIW3UNPZ_WvrQPd4xc_PhYNDF_TgQ&oe=6A66F8F5",
      "posted_at": "2026-06-28T10:59:06.000Z",
      "is_pinned": false,
      "owner_username": "aqu_a_qua",
      "metrics": {
        "views": null,
        "likes": 123,
        "comments": 23
      }
    },
    {
      "post_id": "DZC2SI4TUqG",
      "caption": "물속에서 경험하는 햇빛 샤워 어떤데? ✨\n\n물속으로 쏟아지는 햇빛 줄기를 맞으며,\n한여름 무더운 날의 상쾌하고 청량한 소나기에\n모든 스트레스를 씻어내리는 듯한 힐링을 느껴보세요. 🌊\n\n어디서도 경험할 수 없는 물속 햇빛 샤워,\n올여름엔 함께 하실래요? 🤍\n\n프리다이빙, 머메이드, 스쿠버로 함께 할 수 있는 이 곳은\n시흥 거북섬 웨이브파크 내의 블루라군 다이빙풀입니다.\n\n6월 정식 오픈을 앞두고 있으니 관심 있으신 분들은 서두르세요!\n\nPhotographer :\n@tom_freedive \n\nModel :\n@aqu_a_qua \n\nPla",
      "media_type": "IMAGE",
      "product": "FEED",
      "permalink": "https://www.instagram.com/p/DZC2SI4TUqG/",
      "thumbnail": "https://scontent-lga3-1.cdninstagram.com/v/t51.82787-15/712985157_18139066843553962_3710008000413172198_n.jpg?stp=dst-jpg_e35_p1080x1080_sh2.08_tt6&_nc_ht=scontent-lga3-1.cdninstagram.com&_nc_cat=110&_nc_oc=Q6cZ2gH9X7EdCCltvEDioc9-ho3pXwu6l1aQ3VBZDSB1CLROLvoT7ByYbgGil9IJ43xFMqI&_nc_ohc=qdsOILW-qkoQ7kNvwFPKqhj&_nc_gid=xXe4BxOGw48y3QscrmR9nA&edm=ADp7STQBAAAA&ccb=7-5&oh=00_AQCj00Q5slhts9llwbLgfCnzkycemRG7vgM5P_KHAOhZug&oe=6A670D7C&_nc_sid=c6f216",
      "posted_at": "2026-06-01T13:13:46.000Z",
      "is_pinned": false,
      "owner_username": "tom_freedive",
      "metrics": {
        "views": null,
        "likes": 147,
        "comments": 3
      }
    },
    {
      "post_id": "DWOnHwXmAvM",
      "caption": "고백 하나 하자면, 저는 사실 몸치에요.\n\n머리가 생각하는 것을 몸이 따라가질 못하고,\n한번에 몸의 여러 부분을 각기 컨트롤하는게 특히 잘 안돼요🥹\n\n지난 3월 국제 머메이드 대회에서 여러 사정과 상황이 겹쳐 \n언더워터 댄스 종목으로 출전을 하게 되었는데\n몸치인 저에게는 굉장한 챌린지였어요.\n\n누가 다 짜놓은 안무도 따라 추는게 어려운데\n직접 안무를 짜서 4분짜리 공연을 만들어야한다니..\n\n그래서 저는 안무를 중심으로 접근하기보다는,\n제가 하고 싶은 이야기를 중심으로 풀어나가보았어요.\n\n어렸을 때 제가 정말 좋아했던 게임의 캐릭터가",
      "media_type": "CAROUSEL_ALBUM",
      "product": "FEED",
      "permalink": "https://www.instagram.com/p/DWOnHwXmAvM/",
      "thumbnail": "https://scontent-iad3-1.cdninstagram.com/v/t51.82787-15/656020578_17994242828930063_3625492251072416331_n.jpg?stp=dst-jpg_e35_tt6&_nc_cat=108&ig_cache_key=Mzg1OTE4NTU5NDI1MDM0MjMwOQ%3D%3D.3-ccb7-5&ccb=7-5&_nc_sid=58cdad&efg=eyJ2ZW5jb2RlX3RhZyI6IkNBUk9VU0VMX0lURU0ueHBpZHMuMTQ0MC5zZHIucmVndWxhcl9waG90by5DMyJ9&_nc_ohc=BvjTS4tWlroQ7kNvwEM3PYT&_nc_oc=AdpfP7jV7eSQOocOEnQTrL9tV6qqPWwpCJIl2NOoqgTLZUgao4iTg1BwCZD2aH7iKcQ&_nc_zt=23&_nc_ht=scontent-iad3-1.cdninstagram.com&_nc_gid=SovmdD-fWTyPW1PtoV5AeA&_nc_ss=72689&oh=00_AQAn-DTIGx77ekKPy3YDgo_KoXEdNE5Wis1wys6S6kkuKw&oe=6A6713D5",
      "posted_at": "2026-03-23T13:16:35.000Z",
      "is_pinned": true,
      "owner_username": "aqu_a_qua",
      "metrics": {
        "views": null,
        "likes": 421,
        "comments": 37
      }
    },
    {
      "post_id": "DaiVEDoyXv4",
      "caption": "#협찬 이번 여름 다들 이거 때문에 난리던데?!\n\n이번 여름 트센드라는 레몬코어🍋\n왜 다들 갑자기 레몬에 빠졌나 했더니,\n무채색처럼 반복되는 일상에\n작은 생기를 더하고 싶어서라고 하더라고요.\n\n그래서 저는 레몬 같은 컬러의\n라세린 루미나 수영복과 함께\n여름을 물속에서 즐겨봤어요🌊\n\n은은하게 반짝이는 원단과\n상큼한 옐로우 컬러 덕분에\n햇살 아래에서도 물속에서도\n조금 더 특별하게 느껴지는 여름✨\n\n여러분의 여름 컬러는 무엇인가요?\n\n🧈착용 제품\n@laserin_swim 루미나 버터옐로우\n\n🧈착용 사이즈\n162/50/142 - S사이즈 ",
      "media_type": "VIDEO",
      "product": "REELS",
      "permalink": "https://www.instagram.com/p/DaiVEDoyXv4/",
      "thumbnail": "https://instagram.ffcm1-1.fna.fbcdn.net/v/t51.71878-15/741662231_1043108801505946_7157398459220475636_n.jpg?stp=dst-jpg_e15_tt6&_nc_ht=instagram.ffcm1-1.fna.fbcdn.net&_nc_cat=110&_nc_oc=Q6cZ2gHguQUzzal4T9GJPm_YlOrajXuzEmUsjduMPMvcnFIWk4Ob_S1QN7wJ3Zpqdlqmsj6oMHkpNeDLT4MvTs70MmAz&_nc_ohc=6Zv5YwUooxEQ7kNvwGutsr6&_nc_gid=DiaCyv9eL1KRrWJoo7mjUQ&edm=ADp7STQBAAAA&ccb=7-5&oh=00_AQDzcFV6i9rVzaHkLlOs82QOEkuqyUCZLgbOEVG04nVwuA&oe=6A67056F&_nc_sid=c6f216",
      "posted_at": "2026-07-08T15:11:26.000Z",
      "is_pinned": false,
      "owner_username": "aqu_a_qua",
      "metrics": {
        "views": 5145,
        "likes": 103,
        "comments": 20
      }
    },
    {
      "post_id": "DYucCIcgwQp",
      "caption": "32년 동안 사랑 받았지만 잊혀진 바다를 어시나요?\n\n1987년부터 2019년까지, 화진해수욕장 바로 앞에는\n7번 국도를 따라 동해안을 여행하는 사람들이 \n꼭 들렀던 작은 휴게소가 있었습니다.\n\n동해안의 아름다운 오션뷰를 담은 휴게소는\n여행자들이 멀리서도 일부러 찾곤 하던 곳이었습니다.\n\n그러나 새로운 고속도로가 개통되면서 \n7번 국도를 지나는 사람들은 줄어들고,\n휴게소도 조용히 문을 닫고, \n화진으로 향하는 발길도 점점 끊어져갔습니다.\n\n그러던 즈음, 바다를 담은 숙소 하나가 조용히 시작되고\n그리고 7년이 흐르는 동안 카페도 생기",
      "media_type": "VIDEO",
      "product": "REELS",
      "permalink": "https://www.instagram.com/p/DYucCIcgwQp/",
      "thumbnail": "https://scontent-atl3-1.cdninstagram.com/v/t51.82787-15/706676938_18002537429930063_6738073680513923575_n.jpg?stp=dst-jpg_e15_tt6&_nc_cat=100&ig_cache_key=MzkwNDE4MTIxODc4NjM0NjAyNTE4MDAyNTM3NDIzOTMwMDYz.3-ccb7-5&ccb=7-5&_nc_sid=58cdad&efg=eyJ2ZW5jb2RlX3RhZyI6IkNMSVBTLnhwaWRzLjcyMC5zZHIudmlkZW9fZGVmYXVsdF9jb3Zlcl9mcmFtZS5DMyJ9&_nc_ohc=LnchqKim7j4Q7kNvwHeb0JM&_nc_oc=AdojO1N4Ck5T3M7M1KJFG7ZjO2Pxaypt08VFQ8JsK9ycnl0JTnMLY1LLXgOawK7JZ1SdEXdU_o2_DaKkbssvO-Oo&_nc_zt=23&_nc_ht=scontent-atl3-1.cdninstagram.com&_nc_gid=9AUCGmR-vrqVG3Cb0OL07Q&_nc_ss=7d689&oh=00_AQChoA1S-aWPL5gadUVaR7zC55O3W-unIYzaPYQjUfrVdg&oe=6A670F21",
      "posted_at": "2026-05-24T15:07:39.000Z",
      "is_pinned": false,
      "owner_username": "aqu_a_qua",
      "metrics": {
        "views": 833,
        "likes": 110,
        "comments": 4
      }
    },
    {
      "post_id": "DYV0F63t3YL",
      "caption": "#흑백체험단 으로 간 포항 펜션에서\n침대에 눕질 못하게 했습니다😭\n\n요즘 날씨가 너무 좋죠?\n지난주에 연휴 겸 포항에 놀러갔는데요!\n아니 펜션에서 침대에 눕질 못 했어요\n\n너무 즐길거리가 많아서요😂\n\n✔️사계절 온수풀장\n✔️소나무 사우나\n✔️화진 해수욕장\n✔️개별 바베큐장\n✔️프라이빗 스파\n(요기서 추가금 있는건 바베큐장 세팅비 정도!)\n\n체크인이 끝나자마자 바로 놀기 시작했는데도\n요렇게 풀코스로 즐기고 나니까\n침대에 잠깐 머리 붙일 새가 없더라구요ㅋㅋㅋ\n\n1박 10만원대부터 예약 가능한 이곳은\n포항에 있는 “슬로우오션”의 히든 포",
      "media_type": "VIDEO",
      "product": "REELS",
      "permalink": "https://www.instagram.com/p/DYV0F63t3YL/",
      "thumbnail": "https://scontent-ord5-1.cdninstagram.com/v/t51.71878-15/698680603_27175456418716156_4289229072196946748_n.jpg?stp=dst-jpg_e15_tt6&_nc_cat=106&ig_cache_key=Mzg5NzI1MDE1Nzc4Njc4OTM4Nw%3D%3D.3-ccb7-5&ccb=7-5&_nc_sid=58cdad&efg=eyJ2ZW5jb2RlX3RhZyI6IkNMSVBTLnhwaWRzLjY0MC5zZHIudmlkZW9fZGVmYXVsdF9jb3Zlcl9mcmFtZS5DMyJ9&_nc_ohc=0_ljPDmfxTEQ7kNvwHqK3k8&_nc_oc=Adrrn_W23EL_h4smrb31HyTBLGB8STbArt6O-tA1QcsoHiORQQ8Dgv1OyG1TYLOiAKo&_nc_zt=23&_nc_ht=scontent-ord5-1.cdninstagram.com&_nc_gid=gpaxCj1RoDgIebI6XvDnkw&_nc_ss=7ca8c&oh=00_AQAuTst5FbCSUHLuUPUD7mFUa43Ehu4d22qmyIdqm3a1_g&oe=6A66F7F6",
      "posted_at": "2026-05-15T01:42:42.000Z",
      "is_pinned": false,
      "owner_username": "aqu_a_qua",
      "metrics": {
        "views": 21572,
        "likes": 157,
        "comments": 8
      }
    },
    {
      "post_id": "DYUSQOlKcFl",
      "caption": "파티다~!!! 🎊🎊\nIUPC 2026 대한민국 국제 수중 예술 퍼포먼스 대회 🎆\n\n14일 뮤즈 선발대회\n1번대 대장 @aqu_a_qua 🧜🏻‍♀️🧜🏻‍♀️ \n\n남은 대회 멋지게 잘 머무리해요 :)\n\n@badive_official \n@iupc_official",
      "media_type": "IMAGE",
      "product": "FEED",
      "permalink": "https://www.instagram.com/p/DYUSQOlKcFl/",
      "thumbnail": "https://scontent-det1-1.cdninstagram.com/v/t51.82787-15/673115376_18056093402719490_261349183958540182_n.webp?_nc_cat=100&ig_cache_key=Mzg5NjgxOTg1NzU4NzAyODMyNQ%3D%3D.3-ccb7-5&ccb=7-5&_nc_sid=58cdad&efg=eyJ2ZW5jb2RlX3RhZyI6IkZFRUQueHBpZHMuMTQ0MC5zZHIucmVndWxhcl9waG90by5DMyJ9&_nc_ohc=QciXAY_WNaoQ7kNvwGZ7q1w&_nc_oc=AdopTT72yOSLR_rZ8A_A5wHEN_0IJuMk9WVYduT_9inz8-vqq1CjAFHmfX33XhRZBPg&_nc_zt=23&_nc_ht=scontent-det1-1.cdninstagram.com&_nc_gid=sA3QzsyxqHIIpLA9si-Q1w&_nc_ss=72a8c&oh=00_AQAtFqpXhWKLASJ3JKxhKAsuAtB1cjdHTztiDDYIADxOIg&oe=6A6703AF",
      "posted_at": "2026-05-14T11:12:33.000Z",
      "is_pinned": false,
      "owner_username": "romo_freediving",
      "metrics": {
        "views": null,
        "likes": 3,
        "comments": 10
      }
    },
    {
      "post_id": "DZAcg1jOJ0t",
      "caption": "인어가 짐싸는 법🧳\n\n물속에서의 우아함만 보고\n짐싸는 모습도 우아할거라고 상상하셨나요?\n\n현실은 챙길게 너무 많아서 정신도 없고\n항상 어깨 빠지도록 무거운 짐을\n이고 다니는 것이 인어의 현실...😓\n\n의상이며 소품이며 각종 장비며\n머메이드를 하면서 생긴 짐이 정말 많은데\n도심형 창고인 편안창고를 인어옷장으로\n몇년 째 벌써 잘 이용하고 있답니다💓\n\n창고라고 부동산 알아보고 복잡하게 계약하는게 아니라\n딱 나한테 필요한 공간만큼만, 필요한 개월수로 계약할 수 있으니 취미용 짐이 많은 분들께도 추천해요!\n\n👇🏻편안창고 상담에 대한 보다 더",
      "media_type": "VIDEO",
      "product": "REELS",
      "permalink": "https://www.instagram.com/p/DZAcg1jOJ0t/",
      "thumbnail": "https://scontent-atl3-3.cdninstagram.com/v/t51.82787-15/712267337_18003480341930063_2574849677285161725_n.jpg?stp=dst-jpg_e15_tt6&_nc_ht=scontent-atl3-3.cdninstagram.com&_nc_cat=111&_nc_oc=Q6cZ2gHQXgtE9LWpT0DgdiA3x2JHCZ3M-8fKbIeiPtoe_paA9pv6mrue5Hr4FSoU18Z_4wM&_nc_ohc=3DaJKfjixwgQ7kNvwGZ_-io&_nc_gid=Oung6_fMycuuOSVhropbLg&edm=ADp7STQBAAAA&ccb=7-5&oh=00_AQDw3HeqKcfiuNv8lvOuy_RcgaJEDfBUg4EwmqvZOaNkBw&oe=6A670F8C&_nc_sid=c6f216",
      "posted_at": "2026-05-31T14:57:46.000Z",
      "is_pinned": false,
      "owner_username": "aqu_a_qua",
      "metrics": {
        "views": 5003,
        "likes": 120,
        "comments": 9
      }
    },
    {
      "post_id": "DYcYSIKtwgY",
      "caption": "손님... 제발 객실에서 나가주세요...😭\n\n바다를 담은 풀빌라에 찾아온 낯선 손님\n대체 왜 퇴실을 안하시는 걸까요?\n\n인어 손님도 찾아와서는 떠나질 않는다는\n포항 풀빌라 슬로우오션🩵\n\n인어 손님이 묵은 영상 속 객실은\n물속을 모티프로 디자인된 “웨일” 객실로\n\n거실, 침실, 부엌, 욕조, 루프탑 수영장 \n어디든 잘 보이는 바다뷰가 매력적인 객실이라 \n꼭 한번 하루 지내보시기를 추천드려요☺️\n\n#흑백체험단  #슬로우오션 #포항풀빌라 #포항펜션 #포항숙소",
      "media_type": "VIDEO",
      "product": "REELS",
      "permalink": "https://www.instagram.com/p/DYcYSIKtwgY/",
      "thumbnail": "https://scontent-atl3-3.cdninstagram.com/v/t51.71878-15/703085416_27216561571301741_3319867595487121413_n.jpg?stp=dst-jpg_e15_tt6&_nc_cat=109&ig_cache_key=Mzg5OTA5ODE3NjIzMjU1NjU2OA%3D%3D.3-ccb7-5&ccb=7-5&_nc_sid=58cdad&efg=eyJ2ZW5jb2RlX3RhZyI6IkNMSVBTLnhwaWRzLjY0MC5zZHIudmlkZW9fZGVmYXVsdF9jb3Zlcl9mcmFtZS5DMyJ9&_nc_ohc=Ky-T-PNxPQ8Q7kNvwHXdxmX&_nc_oc=Adqfc4lWSjM8v_Tti2eOgF6FP7xVAdP6ZRjMn3GJjDb1QGF4TctosqXZeH_Z0LswWo4&_nc_zt=23&_nc_ht=scontent-atl3-3.cdninstagram.com&_nc_gid=59K9mvOZotbxBCOscG5Rrg&_nc_ss=72689&oh=00_AQD11_tm_xWDApZqQpL7FtdXZbpkLpT1ACrMAcP-Dv-8Iw&oe=6A66FEBC",
      "posted_at": "2026-05-17T14:45:58.000Z",
      "is_pinned": false,
      "owner_username": "aqu_a_qua",
      "metrics": {
        "views": 1371,
        "likes": 71,
        "comments": 4
      }
    },
    {
      "post_id": "DYZRZ0Kyb65",
      "caption": "#흑백체험단 여기가 한국이라고? 물친자라면 꼭 와봐야하는 풀빌라🩵\nA hidden poll vila in Korea every water lover would obsess over 🩵\n\n마치 인어가 놀러올 것만 같은 이 공간은\n사장님이 ‘물속’을 컨셉으로\n디테일 하나하나 신경 써서 만든 공간이에요.\n\n물결을 닮은 유선형의 통창,\n거실 부엌 침실 욕조 등 주요 공간 모두에서 보이는 바다,\n거실까지 물결이 전해지는 루프탑 수영장,\n그외에도 바다를 연상시키는 각종 오브제까지.\n\n한국에 이런 무드의 풀빌라가 있다니👀\n네이버에 “슬로우오션”",
      "media_type": "VIDEO",
      "product": "REELS",
      "permalink": "https://www.instagram.com/p/DYZRZ0Kyb65/",
      "thumbnail": "https://scontent-mia3-2.cdninstagram.com/v/t51.71878-15/671118202_1325759739478235_1865477149529061364_n.jpg?stp=dst-jpg_e15_tt6&_nc_cat=107&ig_cache_key=Mzg5ODIyMzQ5MzI1OTA1MDY4MQ%3D%3D.3-ccb7-5&ccb=7-5&_nc_sid=58cdad&efg=eyJ2ZW5jb2RlX3RhZyI6IkNMSVBTLnhwaWRzLjY0MC5zZHIudmlkZW9fbmZyYW1lX2NvdmVyX2ZyYW1lLkMzIn0%3D&_nc_ohc=31UmI5Bi1EYQ7kNvwFP2gos&_nc_oc=AdoZnJRK844VViEepneaIEQlQ6QdEfmkmtzckap2DGGZv0LXW2gaEHR1hlzJo1mkgbQ&_nc_zt=23&_nc_ht=scontent-mia3-2.cdninstagram.com&_nc_gid=t3pwJX5gKV_Y9-x46jsX_g&_nc_ss=7ca8c&oh=00_AQC4R7Qaq0PJd-TotFoo4btaNmrzIuzhwY1CivrPjloplA&oe=6A6729A1",
      "posted_at": "2026-05-16T09:58:34.000Z",
      "is_pinned": false,
      "owner_username": "aqu_a_qua",
      "metrics": {
        "views": 208,
        "likes": 31,
        "comments": 0
      }
    },
    {
      "post_id": "DYckmvniduU",
      "caption": "*･ﾟ*✧･ﾟHappy End *･✧･ﾟ*･ﾟ\n\n2026.05.16 | IUPC Day 3\n\n'화색이 돈다'는 표현을 모르는 분이 있다면 이 사진을 보여주세요.\n바로 이것임\n\n3월 대전 엑스포 아쿠아리움에서 보여드렸던 작품을 5월에 재탕해서 나갈 생각에 '편하겠고만~'이라고 생각했던 우리들의 뒷통수.. 아주 그냥 산산조각박살 나버렸어요..\n상상도 못했죠.. 창크기가 이렇게나 변수를 일으킬줄은 ㅋㅋ...ㅋㅋㅋ 모든 것을 다 바꿔야했다....^_____^\n\n취업사기(?) 당한 아쿠레나에게 정말 미안하고.. 또 끝까지 함께 버티며 완주해",
      "media_type": "CAROUSEL_ALBUM",
      "product": "FEED",
      "permalink": "https://www.instagram.com/p/DYckmvniduU/",
      "thumbnail": "https://scontent-atl3-2.cdninstagram.com/v/t51.82787-15/702134515_18371175553204621_4201901409514709292_n.heic?stp=dst-jpg_e35_tt6&_nc_cat=102&ig_cache_key=Mzg5OTE0MzY5MjEzMDY1MTI1Mw%3D%3D.3-ccb7-5&ccb=7-5&_nc_sid=58cdad&efg=eyJ2ZW5jb2RlX3RhZyI6IkNBUk9VU0VMX0lURU0ueHBpZHMuMTQ0MC5zZHIucmVndWxhcl9waG90by5DMyJ9&_nc_ohc=SKLQR7I1owkQ7kNvwHHsCzt&_nc_oc=AdovDc07oaMY-95OaIHegH1J62XXUKokOCdiaG3y3HJOL_jXbj0Lx5q9C5CBMS_tKmw&_nc_zt=23&_nc_ht=scontent-atl3-2.cdninstagram.com&_nc_gid=Pzs3o3DbT7bO1Y8zruACuQ&_nc_ss=7ca8c&oh=00_AQDsvIEkYkUXXNaqYeK94Fafd9tLoCHc0a5TZpfaYXhQkg&oe=6A672249",
      "posted_at": "2026-05-17T16:26:45.000Z",
      "is_pinned": false,
      "owner_username": "woods_rim",
      "metrics": {
        "views": null,
        "likes": 300,
        "comments": 28
      }
    },
    {
      "post_id": "DYXUOe-MATA",
      "caption": "인어가 카페에 가면 어떻게 놀까?🤔\n\n포항에 너무 예쁜 바다뷰 카페에 갔는데\n통창뷰로 가득 담기는 바다가 너무 예뻐서\n인어 세상의 카페에 온 것만 같았어요🩵\n\n그래서 ‘인어가 카페에 간다면 카페를 어떻게 즐길까?’\n하는 상상으로 영상을 한번 만들어봤어요ㅋㅋ\n\n입구부터 물위 징검다리를 건너는 감각적인 포토존에\n인간과 인어 모두 만족시킬만한 다양한 메뉴\n그리고 시원하게 트인 통창에서 보이는 바다뷰까지✨\n\n오픈 6개월만에 무려 10만명이나 다녀갔다는\n포항 카페 아우로라에서 보낸 시간은 힐링 그 자체🥹\n인간도 인어도 모두 좋아할 수밖에 없",
      "media_type": "VIDEO",
      "product": "REELS",
      "permalink": "https://www.instagram.com/p/DYXUOe-MATA/",
      "thumbnail": "https://scontent-dfw5-2.cdninstagram.com/v/t51.71878-15/670865296_1613796116404406_1738351115622900784_n.jpg?stp=dst-jpg_e15_tt6&_nc_cat=107&ig_cache_key=Mzg5NzY3Mjk1ODc3MDkzOTA3Mg%3D%3D.3-ccb7-5&ccb=7-5&_nc_sid=58cdad&efg=eyJ2ZW5jb2RlX3RhZyI6IkNMSVBTLnhwaWRzLjY0MC5zZHIudmlkZW9fbmZyYW1lX2NvdmVyX2ZyYW1lLkMzIn0%3D&_nc_ohc=uAGHJVfgBFkQ7kNvwFqfg3u&_nc_oc=AdrcKImRyWHXNyK-7hD6VV-HNBUp4eRFypFgmS8s0tz3VAA3lHtcCmmkY9ryfW600og&_nc_zt=23&_nc_ht=scontent-dfw5-2.cdninstagram.com&_nc_gid=f6xb-mBWE4gzPfgJZEdyTQ&_nc_ss=72a8c&oh=00_AQBBiT6qI4_CPRyCGpKNqa9lfX99lMtzBxkHJDRQYL1R6A&oe=6A66F51F",
      "posted_at": "2026-05-15T15:36:47.000Z",
      "is_pinned": false,
      "owner_username": "aqu_a_qua",
      "metrics": {
        "views": 1390,
        "likes": 84,
        "comments": 0
      }
    },
    {
      "post_id": "DYYZ-H9mn_N",
      "caption": "#흑백체험단 인어가 사는 물속을 모티프로 한 숙소✨\n\n스토리로 살짝 올렸을 때부터 \n어디냐고 물어보시는 분들이 많았던 곳!\n\n바다를 향해 나있는 곡선이 유려한 형태의 창부터\n수영장의 물빛을 내려받을 수 있는 천장의 창을 비롯해\n거실, 부엌, 객실, 루프탑 수영장 곳곳에서 바다를 느낄 수 있도록 세심하게 디자인된 공간이었어요🩵\n\n객실에 들어오는 순간 그 분위기에\n누가 오시든 바로 인어공주, 왕자님으로 변신 가능🧜🏻‍♀️\n\n시그니처인 거실 통창 뷰 외에도\n객실 내 구석구석 예쁜 디테일들이 많은데\n다음 영상으로 더 소개드려볼게요☺️\n\n𝗅",
      "media_type": "CAROUSEL_ALBUM",
      "product": "FEED",
      "permalink": "https://www.instagram.com/p/DYYZ-H9mn_N/",
      "thumbnail": "https://scontent-ord5-2.cdninstagram.com/v/t51.82787-15/698283636_18001381520930063_6118533062636645670_n.jpg?stp=dst-jpg_e35_tt6&_nc_cat=105&ig_cache_key=Mzg5Nzk3NTE5ODYyNDc0MDE2MA%3D%3D.3-ccb7-5&ccb=7-5&_nc_sid=58cdad&efg=eyJ2ZW5jb2RlX3RhZyI6IkNBUk9VU0VMX0lURU0ueHBpZHMuMTQ0MC5zZHIucmVndWxhcl9waG90by5DMyJ9&_nc_ohc=fFfj5c9PjfYQ7kNvwGoLOtr&_nc_oc=AdqRy-Y3PKk6D-imtfr-So3epM5V6h5imyKCJPyYbkwuPWNQuyyV_CgR6ISOgKFeHVI&_nc_zt=23&_nc_ht=scontent-ord5-2.cdninstagram.com&_nc_gid=_sN37AJyXcgXkCTlTeLzXg&_nc_ss=72289&oh=00_AQB3bT9srcBypjPpnWWzoYRRER0OuHYj06IBhLeM3GDDVA&oe=6A66FB32",
      "posted_at": "2026-05-16T01:36:52.000Z",
      "is_pinned": false,
      "owner_username": "aqu_a_qua",
      "metrics": {
        "views": null,
        "likes": 339,
        "comments": 18
      }
    },
    {
      "post_id": "DYWtEqiz09E",
      "caption": "달빛이 유난히 밝은 밤에..! 🌕🌙\n\n어두운 물속으로 떠오른 커다란 달을 보며 🧜‍♀️\n\n내가 꿈꾸던 순간들이 현실로 펼쳐지는 기분이 들었어요. \n\n나에게는 초승달처럼 흐릿한 듯 가장 선명한 기록이죠. \n\n조금은 상상에 기대어도 괜찮아요, 어쩌면 이게 진짜 나일지도 모르니까요. \n\n여러분의 진짜 “나”는 어디에 있나요?\n\n물속에서 아름다운 달을 만날 수 있는 이 곳은\n@pass9_diving_gumi \n\n물속에서 진짜 자신을 찾아가는 이 분은\n@aqu_a_qua \n\n물속에서 여전히 카메라들고 헤메고 있는 나는\n@tom_freediv",
      "media_type": "IMAGE",
      "product": "FEED",
      "permalink": "https://www.instagram.com/p/DYWtEqiz09E/",
      "thumbnail": "https://instagram.fjan1-1.fna.fbcdn.net/v/t51.82787-15/696617119_18137267575553962_7379465539040705627_n.jpg?stp=dst-jpg_e35_p1080x1080_sh2.08_tt6&_nc_ht=instagram.fjan1-1.fna.fbcdn.net&_nc_cat=110&_nc_oc=Q6cZ2gFnYDzmC8MY9lJpU6OmGp4GJGCL77HgoUEDbTkFtGOlcMVXHnWT5ruWwI81tL58Vyw&_nc_ohc=Sen5shwch84Q7kNvwEwSGKq&_nc_gid=vU0n48Gi-FySwdggJQtCsA&edm=ADp7STQBAAAA&ccb=7-5&oh=00_AQCsuVhnwyC9gxA_6A03NTh9pOVXQOCAUbsJYzZmOnqQ8Q&oe=6A67091E&_nc_sid=c6f216",
      "posted_at": "2026-05-15T09:56:23.000Z",
      "is_pinned": false,
      "owner_username": "tom_freedive",
      "metrics": {
        "views": null,
        "likes": 107,
        "comments": 3
      }
    },
    {
      "post_id": "DYhay1dmuKE",
      "caption": "수영을 못해도 즐길 수 있는 스위밍 행사\n레디투킥 스위밍클럽에 초대받았어요 🏊🏻‍♀️\n\n처음에는 스위밍 클럽이라고 하길래 빡세게 수영하는 모임인가 했는데\n낭독극, 물적응 프로그램, 아쿠아로빅과 같은 프로그램으로\n누구나 물을 즐길 수 있는 축제 같은 행사라고 하더라구요!\n\n저는 3부 아쿠아로빅과 킥킥대회에 참가 예정💓\n인어의 아쿠아로빅 도전기 기대해주시고\n시간되시는 분들은 스위밍 클럽에서 함께 해요🫶\n\n레디투킥 스위밍 클럽 2026\n📍도봉동 실내스포츠센터\n📅 5/31 (일)\n스위밍클럽 예약은 @areyou.readytokick 홈페이",
      "media_type": "CAROUSEL_ALBUM",
      "product": "FEED",
      "permalink": "https://www.instagram.com/p/DYhay1dmuKE/",
      "thumbnail": "https://scontent-lax3-1.cdninstagram.com/v/t51.82787-15/701798897_18001861439930063_4993465687243935611_n.jpg?stp=dst-jpg_e35_tt6&_nc_cat=102&ig_cache_key=MzkwMDUxMTU5OTA4NDA3MjY2Mw%3D%3D.3-ccb7-5&ccb=7-5&_nc_sid=58cdad&efg=eyJ2ZW5jb2RlX3RhZyI6IkNBUk9VU0VMX0lURU0ueHBpZHMuMTQ0MC5zZHIucmVndWxhcl9waG90by5DMyJ9&_nc_ohc=bRKsPUEH8O4Q7kNvwEZEkjX&_nc_oc=AdrT83j1KX7_3h7-ToyhHtmzxjQFuc4iDCDN2id0delMcKIKsvpYhen6w6Q23KdRTcU&_nc_zt=23&_nc_ht=scontent-lax3-1.cdninstagram.com&_nc_gid=Oh0p1NZHSxexDilP6_WORg&_nc_ss=72a8c&oh=00_AQDwF9Vh9f7K0xhP0r95RA-zIQGrMWQ8qwDWA84hruvc1A&oe=6A66FE85",
      "posted_at": "2026-05-19T13:37:13.000Z",
      "is_pinned": false,
      "owner_username": "aqu_a_qua",
      "metrics": {
        "views": null,
        "likes": 72,
        "comments": 5
      }
    },
    {
      "post_id": "DXlxfRNE_QM",
      "caption": "현실은 물장구,,😇💦\n\n#아티스틱스위밍 #artisticswimming #swim",
      "media_type": "VIDEO",
      "product": "REELS",
      "permalink": "https://www.instagram.com/p/DXlxfRNE_QM/",
      "thumbnail": "https://scontent-lax7-1.cdninstagram.com/v/t51.71878-15/681265444_1361777325997633_5816790694089464920_n.jpg?stp=dst-jpg_e15_tt6&_nc_ht=scontent-lax7-1.cdninstagram.com&_nc_cat=101&_nc_oc=Q6cZ2gF7d13GenuKibeI_Z_BnUv1UxJXgu5UpYEMpl87_H5pqN31xaS-6KVAnRNur68NAgE&_nc_ohc=OrGAF4rZz1MQ7kNvwHS2Jt1&_nc_gid=8io7Xs2ygHy3LujLR7dL9g&edm=ADp7STQBAAAA&ccb=7-5&oh=00_AQAij5HkAvgyu6xLppH8n_LYAQK3BXKJzIm0bC2v9B9kqg&oe=6A672144&_nc_sid=c6f216",
      "posted_at": "2026-04-26T09:42:47.000Z",
      "is_pinned": false,
      "owner_username": "xiubeeni",
      "metrics": {
        "views": 32698,
        "likes": 455,
        "comments": 41
      }
    },
    {
      "post_id": "DXeTV9JGjUp",
      "caption": "아름다움은 때로 숨을 조여오는 법.\n\n지독한 고독 끝에 완성된 이 드레스는\n물속에서 비로소 새처럼 날갯짓한다.\n\n이것은 찬란한 추락인가, \n아니면 심해를 향한 마지막 비행인가. \n\n-\n𝗺𝗼𝗱𝗲𝗹 @aqu_a_qua \n𝗽𝗵𝗼𝘁𝗼 @tom_freedive \n\n-\n\n#수중촬영 #수중모델 #수중스냅",
      "media_type": "CAROUSEL_ALBUM",
      "product": "FEED",
      "permalink": "https://www.instagram.com/p/DXeTV9JGjUp/",
      "thumbnail": "https://scontent-dfw6-1.cdninstagram.com/v/t51.82787-15/658933935_17998352600930063_2094932308962320615_n.jpg?stp=dst-jpg_e35_tt6&_nc_cat=103&ig_cache_key=Mzg4MTYyMzI4NTc1OTM4MjQzOQ%3D%3D.3-ccb7-5&ccb=7-5&_nc_sid=58cdad&efg=eyJ2ZW5jb2RlX3RhZyI6IkNBUk9VU0VMX0lURU0ueHBpZHMuMTQ0MC5zZHIucmVndWxhcl9waG90by5DMyJ9&_nc_ohc=rSBPOozyPmQQ7kNvwHSVw2d&_nc_oc=AdqwMykke1tak023ZCf-yURPA-ovPumDWNOjIMM-ubZOSb6GYihtqDqg1_gvnA5n8mw&_nc_zt=23&_nc_ht=scontent-dfw6-1.cdninstagram.com&_nc_gid=pCYTw1oQpUzmraG1AJYbVA&_nc_ss=72689&oh=00_AQCjfWaik7mxWt3UcXReoV0HmKX4uPzEFoyF6GGC0-sXEA&oe=6A670179",
      "posted_at": "2026-04-23T12:03:00.000Z",
      "is_pinned": false,
      "owner_username": "aqu_a_qua",
      "metrics": {
        "views": null,
        "likes": 154,
        "comments": 15
      }
    },
    {
      "post_id": "DYSFNxAE5fE",
      "caption": "아쿠위니레나의 팀 대회 출전을 응원합니다📣📣\n\n매번 대회에 나갈 때마다 마치 이번이 마지막 대회인 것처럼 \n 갖은 고생을 다 하고, 항상 좋은 성적 거둬오는 무적의 팀이자 스릉하는 제 친구들 ❤️\n\n이번 IUPC 대회 역시 팀전으로 출전하네요!\n\n이번에도 꼭 좋은 성적 거두시길 바라고 항상 응원합니다!\n\n식지않는 그녀들의 열정에 건배 🥂\n\n@aqu_a_qua \n@winnie_the_water a.k.a @woods_rim \n@renapark.kr \n\nLocation @no_a_studio \n\n@iupc_official",
      "media_type": "CAROUSEL_ALBUM",
      "product": "FEED",
      "permalink": "https://www.instagram.com/p/DYSFNxAE5fE/",
      "thumbnail": "https://scontent-atl3-3.cdninstagram.com/v/t51.82787-15/696522155_18137094931553962_669238302090720125_n.jpg?stp=dst-jpg_e35_tt6&_nc_cat=108&ig_cache_key=Mzg5NjE5NzQzNDM5MzI4NzU5Mw%3D%3D.3-ccb7-5&ccb=7-5&_nc_sid=58cdad&efg=eyJ2ZW5jb2RlX3RhZyI6IkNBUk9VU0VMX0lURU0ueHBpZHMuMjAwMC5zZHIucmVndWxhcl9waG90by5DMyJ9&_nc_ohc=--wzOSdWjN4Q7kNvwGvUfok&_nc_oc=AdoH_NZGPw_KMFayAfxh7cMwhuQqxHFy3SehhfgugPx8jR4MokXS8P5pZDcBsBT6J3g&_nc_zt=23&_nc_ht=scontent-atl3-3.cdninstagram.com&_nc_gid=P7KuP_kFrKDHa9opLlRphA&_nc_ss=7c689&oh=00_AQAFf_QFCUB9OP4FQNa1rqMZLF2D8msFTG4SWLqPoWL6Sg&oe=6A671848",
      "posted_at": "2026-05-13T14:40:03.000Z",
      "is_pinned": false,
      "owner_username": "tom_freedive",
      "metrics": {
        "views": null,
        "likes": 202,
        "comments": 9
      }
    },
    {
      "post_id": "DYPnyilGP1W",
      "caption": "2026.05.16 (토) / 오후 2시 28분 (KST)\n\n･ﾟ*✧･ﾟ･ﾟ*✧･ﾟ･ﾟ*✧･ﾟ･ﾟ*✧･ﾟ･ﾟ*✧･ﾟ\n\n대한민국의 강렬한 머메이드 팀, <Love the Memory>가\n지난 대만과 한국 국제 머메이드 대회에 이어 새로운 무대인 IUPC에 도파민 팡팡 터지는 무대로 찾아옵니다🎆\n\n대한민국 X, MZ세대 모두 함께 즐길 수 있는 무대인만큼\n아쉽게 3월 대회 직관을 놓치신 분들은 이번 기회를 놓치지 마세요😉\n\n이외에도 토요일에는 가지각색의 매력적인 인어들의 공연이 펼쳐진답니다🎉\n관람객은 별도 통로를 통해 무료 입장 및 관",
      "media_type": "CAROUSEL_ALBUM",
      "product": "FEED",
      "permalink": "https://www.instagram.com/p/DYPnyilGP1W/",
      "thumbnail": "https://scontent-ord5-2.cdninstagram.com/v/t51.82787-15/688523845_18370471654204621_6801889964947035423_n.heic?stp=dst-jpg_e35_tt6&_nc_cat=103&ig_cache_key=Mzg5NTUwMDgxOTU0Mzg3NDg0Mw%3D%3D.3-ccb7-5&ccb=7-5&_nc_sid=58cdad&efg=eyJ2ZW5jb2RlX3RhZyI6IkNBUk9VU0VMX0lURU0ueHBpZHMuMTQ0MC5zZHIucmVndWxhcl9waG90by5DMyJ9&_nc_ohc=IKIUV7G_FMIQ7kNvwFXH0l1&_nc_oc=AdrgNBUmv3p7F-gMc5mMhRZPyJMGVRp75QoYvVfucRq-8C7DtuhSxL1vdw8hy2XSyZA&_nc_zt=23&_nc_ht=scontent-ord5-2.cdninstagram.com&_nc_gid=K-LotvjsHKVHpeWghf6ZQg&_nc_ss=7c689&oh=00_AQBtjPJRaNbtnoyMuJ7WIx7beE4sgAbelOl-hv36IankvA&oe=6A671570",
      "posted_at": "2026-05-12T15:44:27.000Z",
      "is_pinned": false,
      "owner_username": "woods_rim",
      "metrics": {
        "views": null,
        "likes": 122,
        "comments": 6
      }
    },
    {
      "post_id": "DYkTZSnGEBy",
      "caption": "*･✧ 𝐵𝑢𝑑𝑑𝑖𝑒𝑠\n\n'머메이드다이빙을 하면서 가장 기억나는 순간이 언제냐'고 묻는다면 단연코 팀 퍼포먼스가 끝난 뒤 \n서로를 힘껏 껴안았던 그 고요한 순간을 말하고 싶습니다.\n\n눈 앞이 뿌옇게 흐려 잘 보이지 않던 물 속에서도\n함께 숨을 쉬고 숨을 참으며, 같은 호흡으로 서로의 이정표가 되어준 우리들\n\n함께가 아니었다면 수많은 무대들에서 이토록 최선을 다해 해낼 수 없었기에, 이렇게 든든하고 멋진 팀원들을 만날 수 있어 참 감사할 따름입니다. 아마 제 인생에서 더없을 행운이고, 행복일거에요 🍀\n정말 아무나 하지 못할 경험들도, ",
      "media_type": "CAROUSEL_ALBUM",
      "product": "FEED",
      "permalink": "https://www.instagram.com/p/DYkTZSnGEBy/",
      "thumbnail": "https://scontent-ord5-1.cdninstagram.com/v/t51.82787-15/703337089_18371602606204621_2230272175146769532_n.heic?stp=dst-jpg_e35_tt6&_nc_cat=101&ig_cache_key=MzkwMTI4MTEwMDQ1ODcwNTY1Nw%3D%3D.3-ccb7-5&ccb=7-5&_nc_sid=58cdad&efg=eyJ2ZW5jb2RlX3RhZyI6IkNBUk9VU0VMX0lURU0ueHBpZHMuMTQ0MC5zZHIucmVndWxhcl9waG90by5DMiJ9&_nc_ohc=edS8AJDQF3sQ7kNvwFS3Dif&_nc_oc=AdrBXychuWlEPjhC1sFhKvB9S78S0EYaD7Gt3YW9zoZP3dmqrvym-uru0rL9aNn5wIk&_nc_zt=23&_nc_ht=scontent-ord5-1.cdninstagram.com&_nc_gid=bmEIB3LL-eChobd6ce1F-w&_nc_ss=72a8c&oh=00_AQC7U88aTEC_v_1yUo-lScTT_Wo0BrqUlV_HHOwaaxXszg&oe=6A66FF84",
      "posted_at": "2026-05-20T16:30:17.000Z",
      "is_pinned": false,
      "owner_username": "woods_rim",
      "metrics": {
        "views": null,
        "likes": 345,
        "comments": 32
      }
    },
    {
      "post_id": "DYmBZ8lk0n7",
      "caption": "명예(?) 럽더메 팀원으로서 올리는 우당탕탕했던 대회 후기 :\n⠀\n드디어 IUPC 대회가 끝났습니다..! 🥳\n⠀\n매번 대회에 나갈 때마다 그야말로 하얗게 불태우는 것이란 이런 것이라는 걸 증명이라도 하듯이 활활 불태우고 나서는, 정말로 새하얘져서 ”나 이제 대회 출전 따위 안 할끄야”를 시전하지만...\n대회 소식이 또 들리면 어느새 뿅 하고 원상태로 복귀해 눈빛을 반짝이며 대회를 준비하는 친구들. ✨\n⠀\n물생활 하면서 많은 분들을 만났지만, 지금의 럽더메 팀만큼 저와 가장 끈끈하게 이어진 친구들은 없어요. 고생하는 걸 매번 지켜만 ",
      "media_type": "CAROUSEL_ALBUM",
      "product": "FEED",
      "permalink": "https://www.instagram.com/p/DYmBZ8lk0n7/",
      "thumbnail": "https://scontent-ord5-1.cdninstagram.com/v/t51.82787-15/705018337_18137881381553962_6694144182691106987_n.jpg?stp=dst-jpg_e35_tt6&_nc_cat=110&ig_cache_key=MzkwMTc5ODIyNzMyMjQxMDQ1NA%3D%3D.3-ccb7-5&ccb=7-5&_nc_sid=58cdad&efg=eyJ2ZW5jb2RlX3RhZyI6IkNBUk9VU0VMX0lURU0ueHBpZHMuMzI3Ny5zZHIucmVndWxhcl9waG90by5DMyJ9&_nc_ohc=od3tzTsQFlwQ7kNvwGVppKR&_nc_oc=AdqZgnQSM-Ik-iISysV5X3hM8Ch-FQiDrr5Pw-o-D7drD6o17YnOfmWZquPmESJuDLY&_nc_zt=23&_nc_ht=scontent-ord5-1.cdninstagram.com&_nc_gid=eIobi1bdhU5rEpn1pegP_g&_nc_ss=7ca8c&oh=00_AQAfDohSYR5oHAjsfpZ18eb_ZHOJfT9nRSm21Xc_j6qWUg&oe=6A6713CF",
      "posted_at": "2026-05-21T08:31:34.000Z",
      "is_pinned": false,
      "owner_username": "tom_freedive",
      "metrics": {
        "views": null,
        "likes": 184,
        "comments": 11
      }
    },
    {
      "post_id": "DYPYHP9Gjv2",
      "caption": "폰 촬영으로도 화보 찍는 국내바다🌊\n\n예전엔 국내 바다라고 하면 강릉, 강화도 정도였는데\n인어가 되고서부터 다양한 국내 바다를 경험하고 있어요.\n\n그러다가 발견하게 된 정말 아름다운 해변,,\n일몰 시간 즈음 찾아가서 가볍게 핸드폰 촬영을 했는데\n은은한 태양빛과 강렬한 파도의 물결이 \n촬영 원본 그대로도 작품 같이 나오는거 있죠🥹💙\n\n저는 I라서 복작복작 사람 붐비는 곳은 기빨려하는데\n아름다운 해변에 비해 사람도 너무 붐비지 않고\n한적하게 일몰을 즐길 수 있는 곳이었어요\n\n뷰가 너무 좋은 숙소와 카페도\n엎어지면 코닿는 거리에 있는 이",
      "media_type": "CAROUSEL_ALBUM",
      "product": "FEED",
      "permalink": "https://www.instagram.com/p/DYPYHP9Gjv2/",
      "thumbnail": "https://scontent-atl3-1.cdninstagram.com/v/t51.82787-15/691556365_18000924245930063_470531707918117920_n.jpg?stp=dst-jpg_e35_tt6&_nc_cat=106&ig_cache_key=Mzg5NTQzMTYzODg3ODE5NDYwNA%3D%3D.3-ccb7-5&ccb=7-5&_nc_sid=58cdad&efg=eyJ2ZW5jb2RlX3RhZyI6IkNBUk9VU0VMX0lURU0ueHBpZHMuMTQ0MC5zZHIucmVndWxhcl9waG90by5DMyJ9&_nc_ohc=jeGwB0s2SuIQ7kNvwHERuNj&_nc_oc=AdqoodfqC8QspHDTdYEpNTIShVe0mRQmFqd7M_x3GlDnD46GqVUe9uvVjC7-w8XHfxE&_nc_zt=23&_nc_ht=scontent-atl3-1.cdninstagram.com&_nc_gid=X2LJ8bkBd4yYvTbSSFKOkg&_nc_ss=7ca8c&oh=00_AQDjra3LmsGlJembwNdpCVkDHL-z05cV24Gy9E4VG-Xt2A&oe=6A66F777",
      "posted_at": "2026-05-12T13:27:28.000Z",
      "is_pinned": false,
      "owner_username": "aqu_a_qua",
      "metrics": {
        "views": null,
        "likes": 167,
        "comments": 10
      }
    },
    {
      "post_id": "DXtypT0EQiv",
      "caption": "인어공주 아이도루 데뷔?!💖\n\n역대급 디자인으로 피드 사진 하나 올리자마자 \n문의가 많이 받았던 테일 ‘플로팅 라이트’✨\n\n사실 이거 저만 몰래 입으려구 했는데😜\n많은 인어님들이 요청주셔서 결국 주문 오픈했던,,\n\n테일이 도착할 즈음 요거 각자 따로 입을게 아니라\n다같이 한번 입어보면 너무 예쁘겠다 해서\n촬영 세션을 진행했구 감사하게도 다들 함께해 주셨어요\n\n대회 때 2~3명이서 같은 테일 맞춰입은 적은 있는데\n훨씬 많은 인원으로 맞춰입으니 인어 아이돌 된거 같구\n너무너무 예쁘지 않나요🥹💗\n\n구매해주신 인어님들께서 요 테일 데리구\n",
      "media_type": "CAROUSEL_ALBUM",
      "product": "FEED",
      "permalink": "https://www.instagram.com/p/DXtypT0EQiv/",
      "thumbnail": "https://scontent-atl3-1.cdninstagram.com/v/t51.82787-15/683984212_17999171852930063_2339373762858188912_n.jpg?stp=dst-jpg_e35_tt6&_nc_cat=106&ig_cache_key=Mzg4NTk3NTMwNzk5NjQ4ODExNA%3D%3D.3-ccb7-5&ccb=7-5&_nc_sid=58cdad&efg=eyJ2ZW5jb2RlX3RhZyI6IkNBUk9VU0VMX0lURU0ueHBpZHMuMTQ0MC5zZHIucmVndWxhcl9waG90by5DMyJ9&_nc_ohc=x6qbkR7HLkUQ7kNvwHWrF55&_nc_oc=AdpMMhDCDKz3mz-T8BEv4J4nF30D0x-K5yJ7ooS9kl_KT095AUDWboH5ZwfGm7QghWA&_nc_zt=23&_nc_ht=scontent-atl3-1.cdninstagram.com&_nc_gid=A5KMxUZVIdxEEBBGpL73uA&_nc_ss=7ca8c&oh=00_AQDmU-A6nV4Qt4SGdO58S2Uuuev9eavpyzv57g1y4ykePQ&oe=6A670CC2",
      "posted_at": "2026-04-29T12:25:08.000Z",
      "is_pinned": false,
      "owner_username": "aqu_a_qua",
      "metrics": {
        "views": null,
        "likes": 213,
        "comments": 13
      }
    }
  ],
  "fetched_at": "2026-07-23T06:22:20.040141+09:00",
  "ok": true
}