{
  "username": "go.gomma",
  "followers_count": 102268,
  "recent_posts": [
    {
      "post_id": "DarhlBzx4xq",
      "caption": "⠀\n아이는 친구집가고\n남편이랑 물회먹고 카페갈꺼예요\n\n휘뚤마뚤 편한티셔츠 입고💕\n편한게 최고쥬\n@powerhousegym_apparel \n\n#ootd #데일리룩 #fitcheck #40대",
      "media_type": "VIDEO",
      "product": "REELS",
      "permalink": "https://www.instagram.com/p/DarhlBzx4xq/",
      "thumbnail": "https://scontent-iad6-1.cdninstagram.com/v/t51.82787-15/748874306_18073848368703230_4996200673231363308_n.jpg?stp=dst-jpg_e15_tt6&_nc_ht=scontent-iad6-1.cdninstagram.com&_nc_cat=102&_nc_oc=Q6cZ2gF17ZdZsrn3nL896OafAzighn3SP7TGisrzG7JDWGEX7IR5JGL9haI86ydmGKQ-O2SDLDn6khVmyvA1JpIe5TwE&_nc_ohc=f1JupKG53uoQ7kNvwGcwTtz&_nc_gid=IWjl_3pUHr1bB1T1lWVaKw&edm=ADp7STQBAAAA&ccb=7-5&oh=00_AQA7FRXWl6XVIlAZXdeDxzUJuJeydXVkEy8QDmrPbMBayQ&oe=6A671D91&_nc_sid=c6f216",
      "posted_at": "2026-07-12T04:54:55.000Z",
      "is_pinned": false,
      "owner_username": "go.gomma",
      "metrics": {
        "views": 179787,
        "likes": 1422,
        "comments": 118
      }
    },
    {
      "post_id": "DbGQfhiCeGS",
      "caption": "비가와도 걱정없는 글램핑여행!\n빗소리 들으며 수영하고 불멍하고 진짜 좋았다!!\n일박이일은 너무 짧아 >_<\n\n제가 곤이랑 가까워진건 사실\n아이들이 잘어울려서 인데요~\n\n사춘기 아이들은 얼굴을 가려줘야 사진좀 찍어주기 때문에\n둘만 여행다니는것 같아도 늘 아이들과 함께 다니고 있어요\n\n아기때는 나만이 세상의 전부인것 처럼 달라붙어서\n때로는 귀찮았던 아이가,\n이제 내게서 좀 멀어지려고하네요\n이 시기를 지나면 또 내게 다가왔다 때로는 멀어졌다 하겠죠?\n\n이제는 아이의 세상엔 나 말고도 많은것들이 있나봐요\n\n더 많은것들이 있다는 것 보여주고",
      "media_type": "CAROUSEL_ALBUM",
      "product": "FEED",
      "permalink": "https://www.instagram.com/p/DbGQfhiCeGS/",
      "thumbnail": "https://scontent-lga3-2.cdninstagram.com/v/t51.82787-15/754015668_18074812406703230_6613840301896582342_n.jpg?stp=dst-jpg_e35_tt6&_nc_cat=107&ig_cache_key=Mzk0NjkwMzY2NjY2MzI5NDA4NA%3D%3D.3-ccb7-5&ccb=7-5&_nc_sid=58cdad&efg=eyJ2ZW5jb2RlX3RhZyI6IkNBUk9VU0VMX0lURU0ueHBpZHMuMTE2Ni5zZHIucmVndWxhcl9waG90by5DMiJ9&_nc_ohc=mhTt6dAMUHMQ7kNvwHjfmjL&_nc_oc=AdoEF9bpfwmfti4_C7Q-DUB2ZKcF3xN2VtGRLqPoW_oiI_Z0blnpTynGwNbiks_mbtE&_nc_zt=23&_nc_ht=scontent-lga3-2.cdninstagram.com&_nc_gid=eoTEilHaFcaUjtgehqk7OA&_nc_ss=72a8c&oh=00_AQD7DrOopUttVJli0zidj_66mvMJ4GAa-n5rb0RMyiWntg&oe=6A6738F4",
      "posted_at": "2026-07-22T14:01:54.000Z",
      "is_pinned": false,
      "owner_username": "go.gomma",
      "metrics": {
        "views": null,
        "likes": 226,
        "comments": 8
      }
    },
    {
      "post_id": "Da-kXvbRD70",
      "caption": "⠀\n입고 싶었던 카프리 팬츠💕\n운동할 때는 물론, 평소에도 부담 없이 입기 좋은 핏✨\n✔️은은한 광택감과\n✔️트임디테일까지 마음에 쏙🤍\n\n@conchwear \n트임 카프리 팬츠\n\n#협찬 #카프리팬츠 #vlog #outfitoftheday #운동복",
      "media_type": "VIDEO",
      "product": "REELS",
      "permalink": "https://www.instagram.com/p/Da-kXvbRD70/",
      "thumbnail": "https://scontent-mia5-1.cdninstagram.com/v/t51.82787-15/743016957_18074333780703230_5612809448703647330_n.jpg?stp=dst-jpg_e35_p1080x1080_sh2.08_tt6&_nc_ht=scontent-mia5-1.cdninstagram.com&_nc_cat=102&_nc_oc=Q6cZ2gH46ro6lBUkRJjLhwh5S_C3eiG3lELMhr6MCmsZMF87VPU5a0G64VJF0Wst-ZMCbL8w3zH0tATgMlgiscLIEDjP&_nc_ohc=lsFvlgp3wkcQ7kNvwEx6OC7&_nc_gid=Gy41V9MZNTnotpjhXXE8-Q&edm=ADp7STQBAAAA&ccb=7-5&oh=00_AQAVz1Xx6ezJHo9JUyZ9WxI9X7ct3k2hNn6DFOXp-VnC0Q&oe=6A672E33&_nc_sid=c6f216",
      "posted_at": "2026-07-19T14:23:36.000Z",
      "is_pinned": false,
      "owner_username": "go.gomma",
      "metrics": {
        "views": 63998,
        "likes": 601,
        "comments": 34
      }
    },
    {
      "post_id": "DbBTDTuJETx",
      "caption": "⠀\n재밌는거 한다고 들으면 쫓아가서 끼는편😌\n@degrey.korea \n@degrey.official \n\n#운동하는여자 #운동복 #헬스장 #gymlife #motivation",
      "media_type": "VIDEO",
      "product": "REELS",
      "permalink": "https://www.instagram.com/p/DbBTDTuJETx/",
      "thumbnail": "https://scontent-mia5-1.cdninstagram.com/v/t51.82787-15/753248554_18074578490703230_9110422944946856051_n.jpg?stp=dst-jpg_e15_tt6&_nc_ht=scontent-mia5-1.cdninstagram.com&_nc_cat=102&_nc_oc=Q6cZ2gH6jg_W4Y8YP6g3Im2IYGsAA98DrgyBws_aur-buKJ4juWHnqB2n2q4gSMSbboCGxaIa8IpSL80_Kf1vz9AYozD&_nc_ohc=iAF-1s0U0sMQ7kNvwGHcKCf&_nc_gid=6udyTeiKZGL8LsVAcBY4Zg&edm=ADp7STQBAAAA&ccb=7-5&oh=00_AQC_wwMEQD2JJaK8k_yhxbDBrDzkKALF2y9VUtkyigdBeA&oe=6A672B54&_nc_sid=c6f216",
      "posted_at": "2026-07-20T15:53:55.000Z",
      "is_pinned": false,
      "owner_username": "go.gomma",
      "metrics": {
        "views": 24114,
        "likes": 1276,
        "comments": 24
      }
    },
    {
      "post_id": "DbD0RqLoWAW",
      "caption": "⠀\n\n마크피에뉴의 새로운 수영복 ‘씨스타 핑크’를 입어봤습니다.💕\n@markpianuofficial \n\n세미컷 라인이라 움직임이 편하고, 프리다이빙이나 수영할 때도 안정감 있게 착용할 수 있었어요.\n\n탄탄하면서도 가벼운 원단이라 몸을 잘 잡아주는 느낌이 좋았고, 핑크 컬러 덕분에 물속에서도 존재감이 살아납니다\n\n저는 168cm / 58kg, M 사이즈를 착용했는데 정사이즈로 잘 맞았습니다.\n\n#마크피에뉴 #수영복추천 #수영복 #프리다이빙 #수영",
      "media_type": "VIDEO",
      "product": "REELS",
      "permalink": "https://www.instagram.com/p/DbD0RqLoWAW/",
      "thumbnail": "https://instagram.ffcm1-2.fna.fbcdn.net/v/t51.82787-15/750873291_18074680406703230_8812511809256887763_n.jpg?stp=dst-jpg_e35_p1080x1080_sh2.08_tt6&_nc_ht=instagram.ffcm1-2.fna.fbcdn.net&_nc_cat=102&_nc_oc=Q6cZ2gECX6367jcLjO8e3ZKbAYC3VF_G9H-aeY68GhteGVxna5jXQYehxWx6uJLAfm9yt8duc3S1t0GBMIwY9YRuxkwp&_nc_ohc=pRI59TQbp8EQ7kNvwGTOx1y&_nc_gid=NWg10bSE7KACXCZ7klD0YQ&edm=ADp7STQBAAAA&ccb=7-5&oh=00_AQCFReBoaVoaiDqVQiRdcBDpvSClNTn96y9rqOEc7PQ18Q&oe=6A672A04&_nc_sid=c6f216",
      "posted_at": "2026-07-21T15:17:23.000Z",
      "is_pinned": false,
      "owner_username": "go.gomma",
      "metrics": {
        "views": 4794,
        "likes": 147,
        "comments": 12
      }
    },
    {
      "post_id": "Da_ppGeExit",
      "caption": "⠀\n내가 세바스찬 할께, 누가 인어곤쥬님할래?!\n\n물이 무서워도 펀다이버는 될수있어요😌\n5m에서도 이렇게 재밌게 놀슈있구요!\n\n@freediver_g.na \n@diver_anna.mermaid \n\n#프리다이빙 #울산프리다이빙 #부산프리다이빙 #수중촬영",
      "media_type": "CAROUSEL_ALBUM",
      "product": "FEED",
      "permalink": "https://www.instagram.com/p/Da_ppGeExit/",
      "thumbnail": "https://scontent-waw2-2.cdninstagram.com/v/t51.82787-15/752325789_18074415245703230_8687389625295257659_n.jpg?stp=dst-jpg_e35_tt6&_nc_cat=105&ig_cache_key=Mzk0NTA0ODI1MjYzODYzMDU0NA%3D%3D.3-ccb7-5&ccb=7-5&_nc_sid=58cdad&efg=eyJ2ZW5jb2RlX3RhZyI6IkNBUk9VU0VMX0lURU0ueHBpZHMuMTQ0MC5zZHIucmVndWxhcl9waG90by5DMyJ9&_nc_ohc=JpSoS8l-p1UQ7kNvwG5Hto1&_nc_oc=AdomU7b3Z_IBst9VuAToPXHYn4T1UF9dBJyeV_VdF_jEIa5pDG6ACrHiVR88Q7U1iQs&_nc_zt=23&_nc_ht=scontent-waw2-2.cdninstagram.com&_nc_gid=hPAkYqrd0jSxis29An2_5Q&_nc_ss=72a8c&oh=00_AQDtzY5YAHOKyZQ7uqvr9lyF4gEq4EKKNzDfBEQQdTTEAA&oe=6A6720F7",
      "posted_at": "2026-07-20T00:26:58.000Z",
      "is_pinned": false,
      "owner_username": "go.gomma",
      "metrics": {
        "views": null,
        "likes": 401,
        "comments": 41
      }
    },
    {
      "post_id": "Da4Ii9-kd7N",
      "caption": "광안리 출몰 잦은 편\n\ntop @physicalgarments \nbottom @freedom__athletic \n\n#광안리 #스폰지밥 #ootd #부산여행",
      "media_type": "CAROUSEL_ALBUM",
      "product": "FEED",
      "permalink": "https://www.instagram.com/p/Da4Ii9-kd7N/",
      "thumbnail": "https://instagram.fsac1-2.fna.fbcdn.net/v/t51.82787-15/748938739_18073924958703230_2416062141481040727_n.jpg?stp=dst-jpg_e35_tt6&_nc_cat=105&ig_cache_key=Mzk0MjkzNzcyMzY0MzY1NTAzNg%3D%3D.3-ccb7-5&ccb=7-5&_nc_sid=58cdad&efg=eyJ2ZW5jb2RlX3RhZyI6IkNBUk9VU0VMX0lURU0ueHBpZHMuMTQ0MC5zZHIucmVndWxhcl9waG90by5DMyJ9&_nc_ohc=jHpWQ0Qd8dMQ7kNvwEThkAj&_nc_oc=Adp0mzJewJiMtRr9YqfhoBDHXW5MEOaTx0TeoeixWTST2nFFNrv2okWf-I4UAUi9hNo&_nc_zt=23&_nc_ht=instagram.fsac1-2.fna&_nc_gid=o6-rv3bghqyLYzbF-KN3ZA&_nc_ss=72a8c&oh=00_AQDkdA2mNjSRNIic_8SLk9c7lQssGAPeD6Q0OxHXIGRPjQ&oe=6A6721A3",
      "posted_at": "2026-07-17T02:23:05.000Z",
      "is_pinned": false,
      "owner_username": "go.gomma",
      "metrics": {
        "views": null,
        "likes": 297,
        "comments": 11
      }
    },
    {
      "post_id": "Da_ZclKE3od",
      "caption": "⠀\n곧 한국에서도 만나볼 수 있는 짐웨어, 디그레이.\n@degrey.korea\n\n복근모양은 사람마다 다 다르다죠\n6팩인사람도 있고 8개인 사람도 있다던데\n어쩌면 나 2팩 정도가 다가 아닐까🌝\n복근vs막창..\n\n미안한데 막창입니다😌 카레가루 찍는데 어케참음?\n\n#디그레이 #DEGREY #짐웨어 #운동기록 #운동하는여자",
      "media_type": "CAROUSEL_ALBUM",
      "product": "FEED",
      "permalink": "https://www.instagram.com/p/Da_ZclKE3od/",
      "thumbnail": "https://scontent-atl3-2.cdninstagram.com/v/t51.82787-15/751713273_18074397113703230_4839364713405439790_n.jpg?stp=dst-jpg_e35_tt6&_nc_cat=104&ig_cache_key=Mzk0NDk3NTQyNzY4NDg0ODg1OQ%3D%3D.3-ccb7-5&ccb=7-5&_nc_sid=58cdad&efg=eyJ2ZW5jb2RlX3RhZyI6IkNBUk9VU0VMX0lURU0ueHBpZHMuMTMwMC5zZHIucmVndWxhcl9waG90by5DMyJ9&_nc_ohc=7zfMxuyOw_UQ7kNvwExR6nA&_nc_oc=AdpRTAj_bmrpoQbaeG6Y2hFSI4Jk-Rtf8XcexI0ae7T_Wy2iRzx8AdFz_Q8xtiP85D0&_nc_zt=23&_nc_ht=scontent-atl3-2.cdninstagram.com&_nc_gid=5H062T0P7dFj_DQ8NFDD9A&_nc_ss=72a8c&oh=00_AQCVNmlGLK5iQ3nUK5yl66VEp85XY58z5-6CtZKn58yFRw&oe=6A673BED",
      "posted_at": "2026-07-19T22:05:27.000Z",
      "is_pinned": false,
      "owner_username": "go.gomma",
      "metrics": {
        "views": null,
        "likes": 202,
        "comments": 13
      }
    },
    {
      "post_id": "DSjCnM6kQEd",
      "caption": "⠀\n인생이 어떻게 흘러가는지 알수가 없네요\n뚠뚠이도 만족하며 잘 살다\n당뇨이슈로 내나이에 이건 아닌것 같다 겁이나서 찾은 헬스장\n\n지금나 왜 벤치50?! 롸?!\n\n솔직히..솔직히 벤치는 저의 논외운동이였는데🌝🌝\n딱히 뭐 삼두 뭐..🌝🌝크던가말던가ㅋ\n\n왜 되는지 모르겠디만 시키는대로 하니 느는군요😌\n\n삼두이두삼두삼두 왕팔 강조하시는 코치님과\n‘왕팔‘에 화들짝 놀래는 여성회원\n\n왕다리까지는 괜찮은데..이제 종아리도 괜찮은데..\n왕팔까지는 좀.. 아직멀었네요 전\n\n여리여리 추구미..멀어지는 내 추구미..\n\n갸재밌다! 파워리프팅!\n@mad",
      "media_type": "VIDEO",
      "product": "REELS",
      "permalink": "https://www.instagram.com/p/DSjCnM6kQEd/",
      "thumbnail": "https://scontent-iad6-1.cdninstagram.com/v/t51.82787-15/604011863_18047067011703230_3436783767914942759_n.jpg?stp=dst-jpg_e15_tt6&_nc_ht=scontent-iad6-1.cdninstagram.com&_nc_cat=102&_nc_oc=Q6cZ2gEiEqTAl4QQn7jlkoFmKlTk6mHVKfZN4hf5qB4mm_x67RhTTRmXvhuZIk-ST69EBwo&_nc_ohc=wko1pUt7Za4Q7kNvwGtG-jp&_nc_gid=Xd4TDVqT7DzM8mpeVOj4Yw&edm=ADp7STQBAAAA&ccb=7-5&oh=00_AQACMFnuX1jg4NYbuFY3sQntcUbTy0q0O6se408JigiU6A&oe=6A671EE7&_nc_sid=c6f216",
      "posted_at": "2025-12-22T01:37:23.000Z",
      "is_pinned": true,
      "owner_username": "go.gomma",
      "metrics": {
        "views": 41295,
        "likes": 651,
        "comments": 27
      }
    },
    {
      "post_id": "DajyXQkxBOy",
      "caption": "⠀\n📍장소는 지경해변\n화장실 1km 정도 떨어진 곳에 있음\n안쪽 유우명한 동굴포토존이 있어요\n\n지금은 많이 알려졌지만 작은 어촌마을입니다 \n부디부디 머문자리 깨끗하게 흔적없이 떠납시다\n\n#혼자여행 #여행릴스 #브이로그 #picnic #trip",
      "media_type": "VIDEO",
      "product": "REELS",
      "permalink": "https://www.instagram.com/p/DajyXQkxBOy/",
      "thumbnail": "https://scontent-ord5-2.cdninstagram.com/v/t51.82787-15/731441804_18072726569703230_4672373270719185014_n.jpg?stp=dst-jpg_e35_p1080x1080_sh2.08_tt6&_nc_ht=scontent-ord5-2.cdninstagram.com&_nc_cat=102&_nc_oc=Q6cZ2gGSqiS6HMrZCqTQdOIbKrP409azLy6rYzrI_8863DIrtD2OpGQQhW0I9_o7jHPnVMc&_nc_ohc=kHy1nJIS9msQ7kNvwHcXpZQ&_nc_gid=Nq86qDMuESF5iwHFbri3Xw&edm=ADp7STQBAAAA&ccb=7-5&oh=00_AQDThQ29nD4ULhuAkup3W_6DMYw_0MYjpSqsSrsWBl-8gA&oe=6A6746D0&_nc_sid=c6f216",
      "posted_at": "2026-07-09T04:47:16.000Z",
      "is_pinned": false,
      "owner_username": "go.gomma",
      "metrics": {
        "views": 26578,
        "likes": 358,
        "comments": 21
      }
    },
    {
      "post_id": "DLeWFAJxg6d",
      "caption": "⠀\n온종일 뜨개질만 해대던 집순이 뚱보 아줌마,\n세상 밖으로 나와보니 별일이 다 있더라.\n\n새벽에 졸린 눈 비비고 애들 깰까바\n살금살금 비키니 입으면서\n‘우리 제법 미친 아줌마들이야’ 낄낄거리며\n바다에 갔는데 너무너무 재밌었어요\n\n@gon_workout_ \n@e.young_workout \n\n머리를 가만히 놔두지 못하는 곰마.\n여름맞이 뉴헤어!\n긴 머리로 연장했어요!\n\n단발에 옴브레 염색까지,\n머리색만 네 가지가 넘는 고난이도 머리\n과연 연장이 될까…?\n\n깜쪽같이  캘리포니아걸(?)로 만들어주시는 금손🥹\n@dada_hair.offic",
      "media_type": "CAROUSEL_ALBUM",
      "product": "FEED",
      "permalink": "https://www.instagram.com/p/DLeWFAJxg6d/",
      "thumbnail": "https://scontent-waw2-2.cdninstagram.com/v/t51.75761-15/504047570_18026818514703230_3572039939634841806_n.jpg?stp=dst-jpg_e35_tt6&_nc_cat=107&ig_cache_key=MzY2NTQ2NDIyNjg4MzE5MzAxOQ%3D%3D.3-ccb7-5&ccb=7-5&_nc_sid=58cdad&efg=eyJ2ZW5jb2RlX3RhZyI6IkNBUk9VU0VMX0lURU0ueHBpZHMuMTQ0MC5zZHIucmVndWxhcl9waG90by5DMyJ9&_nc_ohc=0UGiI5ukdUsQ7kNvwEiWL8C&_nc_oc=AdpTftojFtGu4a5vYoFewz2Nr6fYeFWsGEVUJLCk0JS2dXIU43XDOEvTOAJ8kc29G8k&_nc_zt=23&_nc_ht=scontent-waw2-2.cdninstagram.com&_nc_gid=j-UHshsmIHro1UATibyiEQ&_nc_ss=72a8c&oh=00_AQAW96JOHCukqERxuP15byHpK5_JQifSC91cnRSUq2AnvA&oe=6A6734AF",
      "posted_at": "2025-06-29T06:10:10.000Z",
      "is_pinned": true,
      "owner_username": "go.gomma",
      "metrics": {
        "views": null,
        "likes": 1304,
        "comments": 68
      }
    },
    {
      "post_id": "DaVfVKkiY9J",
      "caption": "⠀\n인숫타 5년차.. 저도 바디프로필 찍을 기회가 제법 있었는데요\n제가 여러 작가님들 살린줄로만 알어~\n\n부끄럽고 막 그 오글거리는 컨셉속의 나 감당이안됨 웃겨죽음\n한컷찍고 바닥을 데굴데굴 구르는 나, 작가님 속에 천불,\n빠른포기로 우정을 지켜냈다!\n\n역시 빙구같은게 딱 나다😌",
      "media_type": "CAROUSEL_ALBUM",
      "product": "FEED",
      "permalink": "https://www.instagram.com/p/DaVfVKkiY9J/",
      "thumbnail": "https://scontent-ord5-2.cdninstagram.com/v/t51.82787-15/729674404_18071862554703230_491826328621990037_n.jpg?stp=dst-jpg_e35_tt6&_nc_cat=103&ig_cache_key=MzkzMzE4MzcwODIxNzMwNDMyNQ%3D%3D.3-ccb7-5&ccb=7-5&_nc_sid=58cdad&efg=eyJ2ZW5jb2RlX3RhZyI6IkNBUk9VU0VMX0lURU0ueHBpZHMuMTQ0MC5zZHIucmVndWxhcl9waG90by5DMyJ9&_nc_ohc=1uSvfZhTTtUQ7kNvwGHJPJE&_nc_oc=AdpFv29EzdQJcfNNAg2Bd817Fiz-S5ab4YM8DXQKSbA7kF1pZW-DVW64SXih6VztQF6fiUx0GhTS6wJDI5UBNEkh&_nc_zt=23&_nc_ht=scontent-ord5-2.cdninstagram.com&_nc_gid=fJhWb3Fgqk2Egn0UcUt-nw&_nc_ss=72a8c&oh=00_AQDkNI_d5hVJZXLQL1sznAWDSu5aD_36yjCVZCQBAJ1OIg&oe=6A672635",
      "posted_at": "2026-07-03T15:28:46.000Z",
      "is_pinned": false,
      "owner_username": "go.gomma",
      "metrics": {
        "views": null,
        "likes": 445,
        "comments": 63
      }
    },
    {
      "post_id": "DbA6LzJkUF1",
      "caption": "⠀\n아르기닌도 이제 다이소에서 챙기는 시대🤔💯\n\n멀리 갈 필요도, 따로 주문할 필요도 없이\n다이소에서 바로 챙기는 운동 루틴템이에요💪🏻\n\n간편하게 챙기는 아르기닌 한 포⚡\n2개입 1500원이라 가성비 최고👍\n\n운동 전 하나 챙겨 먹으니 펌핑감도 더 기대되고🔥\n과일농축액 배합으로 진짜 맛있어요👍🏻\n\n운동 전 제 필수템으로 정착 완료🎶\n\n@extreme.kr\n\n#익스트림 #익스트림다이소 #다이소추천템 #운동필수템 #다이소아르기닌",
      "media_type": "CAROUSEL_ALBUM",
      "product": "FEED",
      "permalink": "https://www.instagram.com/p/DbA6LzJkUF1/",
      "thumbnail": "https://scontent-atl3-2.cdninstagram.com/v/t51.82787-15/746067703_18074499548703230_270645901264759334_n.jpg?stp=dst-jpg_e35_tt6&_nc_cat=101&ig_cache_key=Mzk0NTQwNzY0MjA3OTg0ODI3OA%3D%3D.3-ccb7-5&ccb=7-5&_nc_sid=58cdad&efg=eyJ2ZW5jb2RlX3RhZyI6IkNBUk9VU0VMX0lURU0ueHBpZHMuMTIwNi5zZHIucmVndWxhcl9waG90by5DMyJ9&_nc_ohc=nLxyMGwDco8Q7kNvwGEl_1r&_nc_oc=AdrTVYzSR8oS-S8Dum3q9O-cs3f-bQnzlCHzdMcyHgje4iW_hBzYgnAns3fHZ8Ez7uE&_nc_zt=23&_nc_ht=scontent-atl3-2.cdninstagram.com&_nc_gid=F_YVSy_zVTbajhNTCZHdow&_nc_ss=7ca8c&oh=00_AQA0GlaePpmgFZFnTqNiSYRZWXiYSenj2wxOzahbqpPChA&oe=6A67378F",
      "posted_at": "2026-07-20T12:10:46.000Z",
      "is_pinned": false,
      "owner_username": "go.gomma",
      "metrics": {
        "views": null,
        "likes": 249,
        "comments": 17
      }
    },
    {
      "post_id": "DYh0xvlTsxE",
      "caption": "오늘 저를 보고 ‘나도 할 수 있을까요?’\n라고 물으시는 분의 이야기를 들었어요.\n이미 저보다 더 많은 노력을 하고 계신 분이셨어요.\n\n저는 운이 좋아 항상 과분한 격려를 받고 있지만\n남모르게 노력하는 분들께 이야기하고 싶어요.\n\n저도 매일매일 스스로를 의심하던 시절이 있었어요.\n입 터졌다고 스스로 한심하다 자책하고,\n내 노력이 부족하다고 몰아붙이고,\n‘나는 저 사람들처럼 되려면 언제까지, 얼마나 해야 하는 거야?’\n남들과 비교하면 막막하기만 했죠.\n\n뒤돌아 해낸 것들을 봐요\n놓지 않고 여기까지 온  자신을 보세요\n\n마음먹고 이틀 ",
      "media_type": "VIDEO",
      "product": "REELS",
      "permalink": "https://www.instagram.com/p/DYh0xvlTsxE/",
      "thumbnail": "https://scontent-den2-1.cdninstagram.com/v/t51.82787-15/702625024_18065369744703230_4011670989942898629_n.jpg?stp=dst-jpg_e15_tt6&_nc_ht=scontent-den2-1.cdninstagram.com&_nc_cat=102&_nc_oc=Q6cZ2gHe2UdBXKJgs4KAR2v2HGQ6iQvxch7HhXf_BaNxVhaBepCWK9zQLHgEQJH-_vJ9oco&_nc_ohc=l4OdhMKEN4MQ7kNvwGEFSNP&_nc_gid=0F7XQJHDWswBRGat820sCA&edm=ADp7STQBAAAA&ccb=7-5&oh=00_AQAE6fpnGKXzWw-nhMXOpt4M1jGCErqaXIMucib5tHXNQw&oe=6A67371B&_nc_sid=c6f216",
      "posted_at": "2026-05-19T17:25:18.000Z",
      "is_pinned": true,
      "owner_username": "go.gomma",
      "metrics": {
        "views": 806673,
        "likes": 19027,
        "comments": 361
      }
    },
    {
      "post_id": "DaiNQYQCcDy",
      "caption": "⠀\n제가 한우물만 팠다면 벌써 프리다이빙 마스터도 했겠지요\n하지만 또 새로운걸 배워봅니다\n워타댄수💃🏻💃🏻\n\n아 순전히 노핀으로 노는법을 익히고 싶어서 시작했고\n선생님께 발레리나같이 이쁜건 못한다고 몇번이나 말씀드렸디만\n나중에 숙련되면 내가 하고싶은 퍼포먼스를 하더라도\n기본을 할줄알아야 하니까 어설퍼도 따라해봅니다\n\n첫날이라 우당탕이지만 강사님 두분이서 영상찍어주는\n황제트레이닝🩶🩶\n\n연습하러 맨날가고싶은 풀장🔥🔥\n\n언더워터댄스가 궁금하시다면⬇️\n@diver_anna.mermaid",
      "media_type": "CAROUSEL_ALBUM",
      "product": "FEED",
      "permalink": "https://www.instagram.com/p/DaiNQYQCcDy/",
      "thumbnail": "https://scontent-ord5-2.cdninstagram.com/v/t51.82787-15/735477144_18072636734703230_1672933482832076822_n.jpg?stp=dst-jpg_e35_tt6&_nc_cat=105&ig_cache_key=MzkzNjc2MjA2NTU4MDI4Nzg4NA%3D%3D.3-ccb7-5&ccb=7-5&_nc_sid=58cdad&efg=eyJ2ZW5jb2RlX3RhZyI6IkNBUk9VU0VMX0lURU0ueHBpZHMuOTE0LnNkci5yZWd1bGFyX3Bob3RvLkMzIn0%3D&_nc_ohc=nVWHaMLUSvsQ7kNvwH9qZNE&_nc_oc=AdrPQ5uUcaLkU8De25Ttc0yF6EzR5d6BTGBwHDGhznnRal46d0BrpTR48irURSUFQG0&_nc_zt=23&_nc_ht=scontent-ord5-2.cdninstagram.com&_nc_gid=XxIDwAJmMWNDKeo7cVZ6NA&_nc_ss=7c289&oh=00_AQASGo-tf9gzxVMoJxrsgHcZxGeFhL4Bq9lthF4JrDouPw&oe=6A673A38",
      "posted_at": "2026-07-08T14:00:57.000Z",
      "is_pinned": false,
      "owner_username": "go.gomma",
      "metrics": {
        "views": null,
        "likes": 545,
        "comments": 41
      }
    },
    {
      "post_id": "DamQBTSkbvu",
      "caption": "⠀\n원소스멀티유즈 좋아하는 편,\n제가 입은 스커트는 @muscle_n_beauty_mnb_official \n\n테니스치마인데요 걍 아무데나 막입소\n레깅스가 붙어있어서 러닝할때도 입었어요\n장거리러너가 아니라 그런지\n다리에 감기는것도 없고 쓸리는것도 없었어요\n\n#추천템 #러닝 #피크닉 #바캉스룩 #바다여행",
      "media_type": "CAROUSEL_ALBUM",
      "product": "FEED",
      "permalink": "https://www.instagram.com/p/DamQBTSkbvu/",
      "thumbnail": "https://scontent-sea5-1.cdninstagram.com/v/t51.82787-15/731131478_18072854642703230_2243244069440347682_n.jpg?stp=dst-jpg_e35_tt6&_nc_cat=109&ig_cache_key=MzkzNzkwMzE5MjM3MzAyMDY0MQ%3D%3D.3-ccb7-5&ccb=7-5&_nc_sid=58cdad&efg=eyJ2ZW5jb2RlX3RhZyI6IkNBUk9VU0VMX0lURU0ueHBpZHMuMTIwNi5zZHIucmVndWxhcl9waG90by5DMyJ9&_nc_ohc=z4e0uPWMu24Q7kNvwEqbrl4&_nc_oc=AdrICO9V8C01GoFfdsZaE2JZyzcSVlUQXrWCrbmDEr0NZ9ERBjRVKVswupiGbewz7Do&_nc_zt=23&_nc_ht=scontent-sea5-1.cdninstagram.com&_nc_gid=cf_L6S2VuVbw-asluukppQ&_nc_ss=7ca8c&oh=00_AQCCyaQnLlFeH9wKVRzQ-kT538vtoOFQpXV3iM1qMjmR8g&oe=6A6726E2",
      "posted_at": "2026-07-10T03:42:04.000Z",
      "is_pinned": false,
      "owner_username": "go.gomma",
      "metrics": {
        "views": null,
        "likes": 407,
        "comments": 17
      }
    },
    {
      "post_id": "DagjRWtk_Zd",
      "caption": "⠀\n운동 잘 해놓고, 클린하게 잘 먹어놓고\n\n주말 광안리 바다에서 먹는 도너츠,\n‘실패‘나 ’포기‘ 라고 생각하지 않아요\n\n도너츠라 생각해요\n왜냐면 도너츠니깐요 욤욤😌\n\n @physicalgarments \n#운동 #운동복 #식단",
      "media_type": "CAROUSEL_ALBUM",
      "product": "FEED",
      "permalink": "https://www.instagram.com/p/DagjRWtk_Zd/",
      "thumbnail": "https://scontent-sjc6-1.cdninstagram.com/v/t51.82787-15/735594972_18072543833703230_886483424623326848_n.jpg?stp=dst-jpg_e35_tt6&_nc_cat=108&ig_cache_key=MzkzNjI4NTg2Mjc2MTgxNzQxOA%3D%3D.3-ccb7-5&ccb=7-5&_nc_sid=58cdad&efg=eyJ2ZW5jb2RlX3RhZyI6IkNBUk9VU0VMX0lURU0ueHBpZHMuMTE4Ni5zZHIucmVndWxhcl9waG90by5DMyJ9&_nc_ohc=G6ExAzb8p-YQ7kNvwGtJ7Z4&_nc_oc=Ado00bwnfdviMNQb_hnSwbX_RZu9kmBd_UIC_UE66RR4S3rQLmN4eiQ1spRibtYqNgGqMNlQ0IigVxEGl2PC0cwi&_nc_zt=23&_nc_ht=scontent-sjc6-1.cdninstagram.com&_nc_gid=uGujIELS89929NpGR2G5wA&_nc_ss=7c689&oh=00_AQC3kAgoXBrGAg1tjJYypCuGojvdlVa0sHmRYKkrpXoKsQ&oe=6A674637",
      "posted_at": "2026-07-07T22:34:51.000Z",
      "is_pinned": false,
      "owner_username": "go.gomma",
      "metrics": {
        "views": null,
        "likes": 857,
        "comments": 39
      }
    },
    {
      "post_id": "DaaZhv5xq-F",
      "caption": "20kg 감량한 45살 언니의 🍑 둥근 힙 프로젝트\n\n비포 사진 속 납작했던 엉덩이를 보면\n지금이 얼마나 큰 변화인지 더 실감하실 거예요.\n\n오늘은 제가 꾸준히 하는 원레그 리니어 핵스쿼트!\n균형 잡기도 어렵고 자극도 확실해서\n힙과 하체를 함께 단련할 때 자주 하는 운동입니다.\n\n처음부터 잘할 필요는 없어요.\n꾸준히 하다 보면 몸은 정말 조금씩 달라집니다.\n\n🍑 힙 운동 루틴이 필요하다면 저장해 두고 따라 해보세요.\n같이 건강하게 변화하고 싶다면 팔로우하고 함께 운동해요. 💪\n\n#힙운동 #힙업 #원레그운동 #40대운동 #운동루틴",
      "media_type": "VIDEO",
      "product": "REELS",
      "permalink": "https://www.instagram.com/p/DaaZhv5xq-F/",
      "thumbnail": "https://scontent-atl3-2.cdninstagram.com/v/t51.82787-15/731158098_18072874154703230_2069422989949312941_n.jpg?stp=dst-jpg_e15_tt6&_nc_ht=scontent-atl3-2.cdninstagram.com&_nc_cat=102&_nc_oc=Q6cZ2gE72Puc8_CtmxKI1ilnzfknTWVh4zvrNL9TrYVQTRZrDRfQ6GomTyTYMZ8FUAtCr-b8mHgy0gnHzoiy1TQmzzRf&_nc_ohc=hiyERI5K3B4Q7kNvwFKVrDY&_nc_gid=bDvZrUqLntgyE8VR72bslg&edm=ADp7STQBAAAA&ccb=7-5&oh=00_AQDjJIUuX1quB3bR1JtP5iMB5dIpvV6TwT41fl0Q8LIsVw&oe=6A671B35&_nc_sid=c6f216",
      "posted_at": "2026-07-05T13:19:10.000Z",
      "is_pinned": false,
      "owner_username": "go.gomma",
      "metrics": {
        "views": 29442,
        "likes": 323,
        "comments": 7
      }
    },
    {
      "post_id": "DaPoRTpEZKa",
      "caption": "파하짐의 새로운 크롭티셔츠✨⠀\n@powerhousegym_apparel \n@powerhousegym_korea \n\n먹고싶은대로 먹고 운동하면 건돼의길😌\n근돼 되고싶은데 그건 또 아무나되는게 아니더라구요 히히\n\n#운동복 #울산운동 #크롭티",
      "media_type": "CAROUSEL_ALBUM",
      "product": "FEED",
      "permalink": "https://www.instagram.com/p/DaPoRTpEZKa/",
      "thumbnail": "https://scontent-ord5-2.cdninstagram.com/v/t51.82787-15/730275090_18071515982703230_2850779427088940023_n.jpg?stp=dst-jpg_e35_tt6&_nc_cat=105&ig_cache_key=MzkzMTUzNDIzNDAxNTQ5Njg5OA%3D%3D.3-ccb7-5&ccb=7-5&_nc_sid=58cdad&efg=eyJ2ZW5jb2RlX3RhZyI6IkNBUk9VU0VMX0lURU0ueHBpZHMuMTQ0MC5zZHIucmVndWxhcl9waG90by5DMyJ9&_nc_ohc=hQw1qM6feIkQ7kNvwGb0pwK&_nc_oc=AdrzdKMhwD8KPTUKjgUgE86-jlzSHmKJIg1HwC1gWvWprtDuDc4jBERgf-oDKwtn4cA&_nc_zt=23&_nc_ht=scontent-ord5-2.cdninstagram.com&_nc_gid=LYiOe9OGTafSAHLuGDYawg&_nc_ss=7c689&oh=00_AQAdyRA970XJ3_g4bM7SDN-Vd0I0Am1onoeVASRJAonX0g&oe=6A671400",
      "posted_at": "2026-07-01T08:51:26.000Z",
      "is_pinned": false,
      "owner_username": "go.gomma",
      "metrics": {
        "views": null,
        "likes": 958,
        "comments": 52
      }
    },
    {
      "post_id": "DaSsDnVRe0l",
      "caption": "⠀\n너네 이두 왜구래여?!?😇\n\n#운동하는여자 #mommy",
      "media_type": "VIDEO",
      "product": "REELS",
      "permalink": "https://www.instagram.com/p/DaSsDnVRe0l/",
      "thumbnail": "https://scontent-lax3-1.cdninstagram.com/v/t51.82787-15/731573234_18071807747703230_8864772858044005822_n.jpg?stp=dst-jpg_e35_p1080x1080_sh2.08_tt6&_nc_ht=scontent-lax3-1.cdninstagram.com&_nc_cat=102&_nc_oc=Q6cZ2gECsvJ_Ij8Ka4zCYqvuVpw7Bg-Nn03i5Wm9bWEn3Y39WVaniP0hZYSjaZ5jRTN7Y5mfPvm_Qp6ORLuHNfpzz9pO&_nc_ohc=s3CVGh53EssQ7kNvwH3-zcm&_nc_gid=tG16sWQXFIyIXAngUogrow&edm=ADp7STQBAAAA&ccb=7-5&oh=00_AQC3Ao1D9zNL4_is45W0UaDMP3V45gIbgSAjyWpX3ZaJVw&oe=6A6734F3&_nc_sid=c6f216",
      "posted_at": "2026-07-02T13:23:22.000Z",
      "is_pinned": false,
      "owner_username": "go.gomma",
      "metrics": {
        "views": 73308,
        "likes": 1073,
        "comments": 61
      }
    },
    {
      "post_id": "Dap3ZNlEZHI",
      "caption": "⠀\n폭력적인 초코 기세에 놀래버림..\n아침에 수영하고 물회멋는 주말💕\n\n물회 좋아하시면 울산오시거든\n📍진주횟집 들려보세요\n2인이상 주문하면 매운탕도 주심\n\n@powerhousegym_apparel\n\n#ootd #일상복 #40대코디 #여름코디 #짐웨어",
      "media_type": "CAROUSEL_ALBUM",
      "product": "FEED",
      "permalink": "https://www.instagram.com/p/Dap3ZNlEZHI/",
      "thumbnail": "https://scontent-ord5-1.cdninstagram.com/v/t51.82787-15/732302020_18073060364703230_8606340739620061402_n.jpg?stp=dst-jpg_e35_tt6&_nc_cat=108&ig_cache_key=MzkzODkyMTcyMTU3ODc3NDY0Ng%3D%3D.3-ccb7-5&ccb=7-5&_nc_sid=58cdad&efg=eyJ2ZW5jb2RlX3RhZyI6IkNBUk9VU0VMX0lURU0ueHBpZHMuMTE5OC5zZHIucmVndWxhcl9waG90by5DMyJ9&_nc_ohc=URIwLJLeHR4Q7kNvwE6qiVz&_nc_oc=AdrkdkDTBVeiZoSFvFUFarO7f06DYL1dXP_zB2SPwT44qi-FRw6t2MoP0kXNrzinr47vZ2O4oz_YdYtD-fJ5D-F9&_nc_zt=23&_nc_ht=scontent-ord5-1.cdninstagram.com&_nc_gid=xOdZ5cMUBV8-fGUXMrF3JQ&_nc_ss=72289&oh=00_AQABdsnwo0yAZcMhHwQai2zJ093kkuT5A8ha3fkbCcxMjQ&oe=6A67373F",
      "posted_at": "2026-07-11T13:23:51.000Z",
      "is_pinned": false,
      "owner_username": "go.gomma",
      "metrics": {
        "views": null,
        "likes": 2107,
        "comments": 35
      }
    },
    {
      "post_id": "DZwex91xihu",
      "caption": "안 쳐다볼순 없긴 해😌\n\n화나신줄.. 그럴꺼면 나 끼워줘요\n다섯이서 수다떨자💕\n\n머리를 가만안둬 이번엔 파마를 했는데요😌\n내돈내산 머리맛집 @mjone.__jin \n\n#울산미용실추천",
      "media_type": "VIDEO",
      "product": "REELS",
      "permalink": "https://www.instagram.com/p/DZwex91xihu/",
      "thumbnail": "https://scontent-ord5-2.cdninstagram.com/v/t51.82787-15/723208769_18069870338703230_885118837315954032_n.jpg?stp=dst-jpg_e15_tt6&_nc_ht=scontent-ord5-2.cdninstagram.com&_nc_cat=102&_nc_oc=Q6cZ2gEfcDIGKy77TfFhuI38srOf_u7JLdyW-B2G0E6AAftUMOHoFZgHsxemtEckwP8XxDc&_nc_ohc=e46CWyAQgxcQ7kNvwGBwynx&_nc_gid=Ey9WbuA3rKpAO9hEKnCfJA&edm=ADp7STQBAAAA&ccb=7-5&oh=00_AQDhb3MAuJ_-dtAP4A_7350jC_L_SYPP4ACBVg96Aei7Yg&oe=6A674049&_nc_sid=c6f216",
      "posted_at": "2026-06-19T06:34:24.000Z",
      "is_pinned": false,
      "owner_username": "go.gomma",
      "metrics": {
        "views": 29108,
        "likes": 221,
        "comments": 14
      }
    },
    {
      "post_id": "DZ-Bw8zxPjb",
      "caption": "고민해결사누\n\n어쩌면 간단한 문제거든요\n물론 디테일한 부분에서는 간단하게 설명할수 없는\n운동법이 존재하겠지만\n\n저같은 일반인은 그냥 하는게 첫번째,\n징징거리면 아닥하고 걍 하라고 하는\nT레이너 친구들,\n(물론 착하게 말했지만 내귀에 이렇게들림ㅋ)\n\n질문을 할땐 똥고집 버리고 대답을 수용하겠다는 자세로\n시키는대로 해봐야죠 그래도 안변하면 고소하겠습니다",
      "media_type": "VIDEO",
      "product": "REELS",
      "permalink": "https://www.instagram.com/p/DZ-Bw8zxPjb/",
      "thumbnail": "https://scontent-ord5-2.cdninstagram.com/v/t51.82787-15/729819914_18070427612703230_2237203092497788797_n.jpg?stp=dst-jpg_e15_fr_p1080x1080_tt6&_nc_ht=scontent-ord5-2.cdninstagram.com&_nc_cat=102&_nc_oc=Q6cZ2gHTpfVBfe4PmILb1L9mW8nMAN7XSPVJdIQJQ3_xcGxwDjyHcG91_-MPlHy_hiUB8AU&_nc_ohc=WodPoqdLHvsQ7kNvwH6pjsr&_nc_gid=fYPwnmHxinDzgdR4QSsNJA&edm=ADp7STQBAAAA&ccb=7-5&oh=00_AQAmDQ-y3VzF_WjJHo36OoppCm6gWteb7i7kxD3MeMJ32g&oe=6A672936&_nc_sid=c6f216",
      "posted_at": "2026-06-24T12:48:47.000Z",
      "is_pinned": false,
      "owner_username": "go.gomma",
      "metrics": {
        "views": 59719,
        "likes": 558,
        "comments": 37
      }
    },
    {
      "post_id": "DZ6st3zx49e",
      "caption": "40넘으면 다 칭구쟈나\n\n짧은 클립속의 내 모습은 그냥 가장 잘나온 모습일뿐\n저는 그다지 동안이 아니라요\n\n팔자주름 죠지러 조만간 가려고요😉",
      "media_type": "VIDEO",
      "product": "REELS",
      "permalink": "https://www.instagram.com/p/DZ6st3zx49e/",
      "thumbnail": "https://scontent-ord5-2.cdninstagram.com/v/t51.82787-15/729451781_18070438151703230_778493318817251908_n.jpg?stp=dst-jpg_e35_p1080x1080_sh2.08_tt6&_nc_ht=scontent-ord5-2.cdninstagram.com&_nc_cat=102&_nc_oc=Q6cZ2gHhBSKQRRxStw80ALHmMNq84igC-JQvlOSAx5S-ytfMZ-Q14EWCs6jM0TgeLRS_qTg&_nc_ohc=GvlJotpfkHUQ7kNvwFtuC8i&_nc_gid=o1n6YOApYTwrHYwbf9rhAw&edm=ADp7STQBAAAA&ccb=7-5&oh=00_AQDwc1OJ5l0FspDkPZy9yr_4jz2Qdyn1QliYlpGJwvCZuQ&oe=6A6737A5&_nc_sid=c6f216",
      "posted_at": "2026-06-23T05:47:26.000Z",
      "is_pinned": false,
      "owner_username": "go.gomma",
      "metrics": {
        "views": 275311,
        "likes": 2103,
        "comments": 114
      }
    },
    {
      "post_id": "DaKDsc0kTMT",
      "caption": "⠀\n내 알고리즘이 패들보드타고\n피자먹는 외국인들로 도배된 사연\n피자부럽🌝 \n\n#패들보드 #여름 #paddleboarding #운동하는여자 #여행",
      "media_type": "CAROUSEL_ALBUM",
      "product": "FEED",
      "permalink": "https://www.instagram.com/p/DaKDsc0kTMT/",
      "thumbnail": "https://scontent-phl2-1.cdninstagram.com/v/t51.82787-15/735476140_18071178743703230_5091521265469368418_n.jpg?stp=dst-jpg_e35_tt6&_nc_cat=106&ig_cache_key=MzkyOTk2NzIzMDc3NTEwMzEyOQ%3D%3D.3-ccb7-5&ccb=7-5&_nc_sid=58cdad&efg=eyJ2ZW5jb2RlX3RhZyI6IkNBUk9VU0VMX0lURU0ueHBpZHMuMTQ0MC5zZHIucmVndWxhcl9waG90by5DMyJ9&_nc_ohc=ROS3lWN616EQ7kNvwGKDznl&_nc_oc=AdoiyVEKAl98icfcLa2hcvgM400qNUcJbTx1XBg7uP1awOkzR6IMHzMsLFUVV_Zysw0&_nc_zt=23&_nc_ht=scontent-phl2-1.cdninstagram.com&_nc_gid=IhHKvAV_Efl16niiITglKA&_nc_ss=72a8c&oh=00_AQBPAvDQNh-urtxHbqrlfkugl_TXl6vJbsC3fYO9oTfPbA&oe=6A673603",
      "posted_at": "2026-06-29T04:55:38.000Z",
      "is_pinned": false,
      "owner_username": "go.gomma",
      "metrics": {
        "views": null,
        "likes": 478,
        "comments": 23
      }
    },
    {
      "post_id": "DaSzsnQEVzt",
      "caption": "⠀\n운동하고 먹고 달리고 슬랑이만지고 병원가고\n요즘 내 포토덤프✨\n\n맥주가 당기는 여름밤입니다.\n최근 혼자 호프집에 가서 맥주를 마셨는데 왕 재밌었어요!\n주부는 밤에 노는 게 흔치 않아 그런 것 같아요.\n\n파인애플샤베트가 8,500원이나 하길래\n당연히 파인애플이 녹으면 먹고 가는 건 줄 알고 기다렸는데…\n그것까지 먹는 사람은 못 봤다고..😇\n\n혼자 와서 파인애플 뜯어먹는 사람 될 뻔했잖아요..\n\n@physicalgarments \n피지컬가먼츠 홀터넥집업+ 4.5부 바이커 레깅스💕\n\n#운동하는여자 #쉬인깡 #러닝 #헬스 #슬랑이",
      "media_type": "CAROUSEL_ALBUM",
      "product": "FEED",
      "permalink": "https://www.instagram.com/p/DaSzsnQEVzt/",
      "thumbnail": "https://scontent-atl3-1.cdninstagram.com/v/t51.82787-15/731131643_18071716295703230_7814557171111569309_n.jpg?stp=dst-jpg_e35_tt6&_nc_cat=100&ig_cache_key=MzkzMjQzMDQzNDA1NDkxMTg2OA%3D%3D.3-ccb7-5&ccb=7-5&_nc_sid=58cdad&efg=eyJ2ZW5jb2RlX3RhZyI6IkNBUk9VU0VMX0lURU0ueHBpZHMuMTQ0MC5zZHIucmVndWxhcl9waG90by5DMyJ9&_nc_ohc=0hTKLDH4G2QQ7kNvwH-wnaA&_nc_oc=AdoLhZ6hOs9MF3ka6umg-3UBnOnfxn6-oFHT1s2uJM_ROjNlMscqnKZqKhUOhdfLBYc&_nc_zt=23&_nc_ht=scontent-atl3-1.cdninstagram.com&_nc_gid=-7o0dnZlZdyDVr2XHgr5QA&_nc_ss=72a8c&oh=00_AQBp0MvP9VYDgjww4vyXkIHMQiqW1Q2igvF7UTfy3b8LVQ&oe=6A672E76",
      "posted_at": "2026-07-02T14:29:00.000Z",
      "is_pinned": false,
      "owner_username": "go.gomma",
      "metrics": {
        "views": null,
        "likes": 673,
        "comments": 38
      }
    },
    {
      "post_id": "DaEsW7kRN4i",
      "caption": "심지어 같이 운동 하던중도 아니였어요..\n운동하다 덤벨던지고 격려해주러 오는 운동친구 태그@\n\n#운동친구 #gymbuddy",
      "media_type": "VIDEO",
      "product": "REELS",
      "permalink": "https://www.instagram.com/p/DaEsW7kRN4i/",
      "thumbnail": "https://scontent-atl3-2.cdninstagram.com/v/t51.82787-15/731014368_18070842827703230_1600698610714523152_n.jpg?stp=dst-jpg_e15_tt6&_nc_ht=scontent-atl3-2.cdninstagram.com&_nc_cat=102&_nc_oc=Q6cZ2gF4yfHV7xRlTDF3nv5YuyYT56BlUtPgYxtDGdu6aBlGjufXL_EuHEEqr2xQOT6Qyn8&_nc_ohc=a7zdw5Tx4MsQ7kNvwEm4MJ_&_nc_gid=N603Bse0J2KAiBHu7KVYGw&edm=ADp7STQBAAAA&ccb=7-5&oh=00_AQD_KbkzYspXJPpo47EV0CojAHKjMwZYB37AbRRmiXhxow&oe=6A674544&_nc_sid=c6f216",
      "posted_at": "2026-06-27T02:56:51.000Z",
      "is_pinned": false,
      "owner_username": "go.gomma",
      "metrics": {
        "views": 45959,
        "likes": 302,
        "comments": 17
      }
    },
    {
      "post_id": "DafwCODiU7P",
      "caption": "⠀\n뛰다가 비오면 핫도그쇼핑 합법적😌\n물론 딸내미들 심부름이였지\n\n아이 학원대기시간에 가볍게 남의 동네 뛰기\n길을몰라..\n\n슬리브리스,레깅스 모두\n@gacksung\n\n#러닝 #러닝복 #running",
      "media_type": "CAROUSEL_ALBUM",
      "product": "FEED",
      "permalink": "https://www.instagram.com/p/DafwCODiU7P/",
      "thumbnail": "https://instagram.fagc1-2.fna.fbcdn.net/v/t51.82787-15/740288585_18072493244703230_1773565911033392617_n.jpg?stp=dst-jpg_e35_tt6&_nc_cat=111&ig_cache_key=MzkzNjA2ODkyNTE5NjI3MDM0Ng%3D%3D.3-ccb7-5&ccb=7-5&_nc_sid=58cdad&efg=eyJ2ZW5jb2RlX3RhZyI6IkNBUk9VU0VMX0lURU0ueHBpZHMuMTIwNi5zZHIucmVndWxhcl9waG90by5DMyJ9&_nc_ohc=J-9zuqtkV_4Q7kNvwHGEiSi&_nc_oc=AdoK_oRYtzWFXUsaVHb5VytUXD5_QXWiT5al52sl5Wo7-cBcztabHfp6JMk5eIe6hvk&_nc_zt=23&_nc_ht=instagram.fagc1-2.fna&_nc_gid=bhSou5br1V9FO2poM9_wrg&_nc_ss=72289&oh=00_AQBZX548RIBRLwDtjicnuRHT3UE2VJFE6Qp8ZXifZBPELQ&oe=6A6731A7",
      "posted_at": "2026-07-07T15:07:08.000Z",
      "is_pinned": false,
      "owner_username": "go.gomma",
      "metrics": {
        "views": null,
        "likes": 469,
        "comments": 27
      }
    },
    {
      "post_id": "DaOjz5vzjMV",
      "caption": "세종목만 한거 아니고\n세개만 찍은거😌\n\n보통 근력 1~2시간,\n유산소 30분~1시간 \n스트레칭,샤워까지 하면 4시간 정도걸리죠~\n전 오래있는 편도 아님,\n심지어 샤워하고 나왔는데 아직도 안가고 운동하고 계신분들도 있는걸요..\n무셔워 헬창~\n\n운동복 @physicalgarments \n#피지컬가먼츠\n\n#운동하는여자 #운동복 #헬스 #40대다이어트",
      "media_type": "VIDEO",
      "product": "REELS",
      "permalink": "https://www.instagram.com/p/DaOjz5vzjMV/",
      "thumbnail": "https://scontent-sjc6-1.cdninstagram.com/v/t51.82787-15/730189082_18071458685703230_5759334692858384202_n.jpg?stp=dst-jpg_e15_tt6&_nc_ht=scontent-sjc6-1.cdninstagram.com&_nc_cat=102&_nc_oc=Q6cZ2gGFU2OKGeMBvB5VrGEfpKI77Lk1ht00BJPt83eUUt4Hr6Oygx1bbDmmHnJVOD1yD68&_nc_ohc=QvLLBlppJGoQ7kNvwGw8r23&_nc_gid=wxViAlnkkgIO0Pz6murVDg&edm=ADp7STQBAAAA&ccb=7-5&oh=00_AQDFE9kRCqOy4q_IZc0poMTbmSqjdgK5ApTUj6RZ4W_tCQ&oe=6A672B3A&_nc_sid=c6f216",
      "posted_at": "2026-06-30T22:54:09.000Z",
      "is_pinned": false,
      "owner_username": "go.gomma",
      "metrics": {
        "views": 37242,
        "likes": 474,
        "comments": 19
      }
    },
    {
      "post_id": "DaBNG4RE6Ft",
      "caption": "저의 비루한 하체, 나름 애쓰고 있는데요.\n발가락, 무릎, 관절에 제한이 있어서 좋아지는 게 쉽지 않네요.\n\n써글..해보는데까진 해봐야죠\n운동영상 다찍진 못해서 그림기리왔어요\n\n오늘은\n✔️케틀벨사이드런지\n✔️스쿼트\n✔️파워레그프레스\n✔️힙쓰러스트\n✔️불가리안스플릿스쿼트\n✔️스티프데드리프트\n✔️백익스텐션\n✔️유산소\n\n이렇게 했어요 3시간 30분 걸렸어요..\n\n중량도 집나가서 고반복으로 하려고 했는데\n힙쓰러스트 이후 기력이 쇠진해서..😇\n\n양배추식단을 몇일 할것 같아요!\n왜냐면 양배추가 맛탱이가기 일보직전이라✨\n\n예쁜 운동복 상,하의모",
      "media_type": "CAROUSEL_ALBUM",
      "product": "FEED",
      "permalink": "https://www.instagram.com/p/DaBNG4RE6Ft/",
      "thumbnail": "https://scontent-iad3-1.cdninstagram.com/v/t51.82787-15/729784896_18070633007703230_4904593133274358539_n.jpg?stp=dst-jpg_e35_tt6&_nc_cat=110&ig_cache_key=MzkyNzQ3MDczNjc1MTI5OTE5OA%3D%3D.3-ccb7-5&ccb=7-5&_nc_sid=58cdad&efg=eyJ2ZW5jb2RlX3RhZyI6IkNBUk9VU0VMX0lURU0ueHBpZHMuMTEyNC5zZHIucmVndWxhcl9waG90by5DMyJ9&_nc_ohc=V8uQsGzIIcgQ7kNvwEF_mAB&_nc_oc=AdocrYnfONE8-q8_dAbNZhL53xtTIVz0GtLI1DGbXpYSWV5WMWjyfjTUsZj0qA5sUGU&_nc_zt=23&_nc_ht=scontent-iad3-1.cdninstagram.com&_nc_gid=DNWN0ozdPar90CzU1_aNFw&_nc_ss=72689&oh=00_AQBfopVHG8EYip4K1NUvcu6RzyWTLfSwf9Mz0HDVwzAP6Q&oe=6A6719A1",
      "posted_at": "2026-06-25T18:24:43.000Z",
      "is_pinned": false,
      "owner_username": "go.gomma",
      "metrics": {
        "views": null,
        "likes": 950,
        "comments": 45
      }
    },
    {
      "post_id": "DaxgtIxESTd",
      "caption": "⠀\n왠지 건장해보이는 머메이드 랄까나\n@laserin_swim \n\n물속에서도 편안함과 핏, 둘 다 포기 못하는 사람🙋🏻‍♀️\n\n크리스탈 웨이브 레이어링 디자인이 은은하게 빛나서 물속에서\n더 예쁘게 표현되더라고요. 💙✨\n\n서포트력이 좋아 움직임이 많아도\n안정감 있게 착용할 수 있었어요.\n\n사이즈 참고하실 분들을 위해!\n📏 168cm / 58kg\nM 사이즈 착용\n저는 타이트하게 딱 맞는 핏으로 편하게 입었습니다.\n세미하이컷으로 엉천도 넉넉해서 노출에 부담이 없어요!\n\n물속에서도 디자인과 착용감 모두 만족했던 수영복🤍\n\n#협찬 #수영복추",
      "media_type": "CAROUSEL_ALBUM",
      "product": "FEED",
      "permalink": "https://www.instagram.com/p/DaxgtIxESTd/",
      "thumbnail": "https://scontent-ord5-1.cdninstagram.com/v/t51.82787-15/734807963_18073513400703230_3372034022663136536_n.jpg?stp=dst-jpg_e35_tt6&_nc_cat=108&ig_cache_key=Mzk0MTA3MjY0ODg5NzIxMzIwMQ%3D%3D.3-ccb7-5&ccb=7-5&_nc_sid=58cdad&efg=eyJ2ZW5jb2RlX3RhZyI6IkNBUk9VU0VMX0lURU0ueHBpZHMuMTIwNi5zZHIucmVndWxhcl9waG90by5DMyJ9&_nc_ohc=FOnTOFLKHvQQ7kNvwGiIsCk&_nc_oc=AdoIfzPuOWJZKHro8hjSSFYS6AA_znsUL6_pLo42d6_qdythur3J7lppdkkWaTn7bvwTI7rug7mmGtLW321-sy4C&_nc_zt=23&_nc_ht=scontent-ord5-1.cdninstagram.com&_nc_gid=1keWb_SH_CKJmNVKVgFaJw&_nc_ss=78689&oh=00_AQClVzxTZ0MJTGz0EnAI-N_AO5h9_TYGXUnrTzq5q8OEiA&oe=6A6743F4",
      "posted_at": "2026-07-14T12:39:31.000Z",
      "is_pinned": false,
      "owner_username": "go.gomma",
      "metrics": {
        "views": null,
        "likes": 781,
        "comments": 37
      }
    },
    {
      "post_id": "DazTE2kxUC0",
      "caption": "@laserin_swim \n영상으로 말아보는 개인연습 로그북\n\n#라세린수영복 #프리다이빙 #언더워터댄스 #수영장 #수영복",
      "media_type": "VIDEO",
      "product": "REELS",
      "permalink": "https://www.instagram.com/p/DazTE2kxUC0/",
      "thumbnail": "https://scontent-ord5-2.cdninstagram.com/v/t51.82787-15/748306270_18073635326703230_4210855082029712913_n.jpg?stp=dst-jpg_e15_tt6&_nc_ht=scontent-ord5-2.cdninstagram.com&_nc_cat=102&_nc_oc=Q6cZ2gFR6tDM2yi9EeWr5udX6sb5lw3X4D5uAbIWX6Vnjo2bWGmhxD6MXnOlR70kqzbBXj5JYgAkYYqU0DP-Vn77EZiF&_nc_ohc=YmyWf44HXXwQ7kNvwGRVK81&_nc_gid=VhjVbJxuUksuhw_SKE--IQ&edm=ADp7STQBAAAA&ccb=7-5&oh=00_AQAwodEE10Wzz_DBkOV5hw7drd4KNnLfwe5pGRz2Agt6dw&oe=6A675996&_nc_sid=c6f216",
      "posted_at": "2026-07-15T05:26:18.000Z",
      "is_pinned": false,
      "owner_username": "go.gomma",
      "metrics": {
        "views": 25265,
        "likes": 474,
        "comments": 16
      }
    }
  ],
  "fetched_at": "2026-07-23T09:06:28.198264+09:00",
  "ok": true
}